{
    "verses": [
        {
            "id": 531,
            "verse_number": 38,
            "verse_key": "4:38",
            "hizb_number": 9,
            "rub_el_hizb_number": 34,
            "ruku_number": 67,
            "manzil_number": 1,
            "sajdah_number": null,
            "text_uthmani_simple": "والذين ينفقون امولهم رئاء الناس ولا يؤمنون بالله ولا باليوم الءاخر ومن يكن الشيطن له قرينا فساء قرينا",
            "text_uthmani": "وَٱلَّذِينَ يُنفِقُونَ أَمْوَٰلَهُمْ رِئَآءَ ٱلنَّاسِ وَلَا يُؤْمِنُونَ بِٱللَّهِ وَلَا بِٱلْيَوْمِ ٱلْـَٔاخِرِ ۗ وَمَن يَكُنِ ٱلشَّيْطَـٰنُ لَهُۥ قَرِينًا فَسَآءَ قَرِينًا",
            "page_number": 85,
            "juz_number": 5,
            "words": [
                {
                    "id": 39566,
                    "position": 1,
                    "char_type_name": "word",
                    "v1_page": 85,
                    "text_uthmani": "وَٱلَّذِينَ",
                    "text_indopak": "وَالَّذِيۡنَ",
                    "code_v1": "ﭑ",
                    "page_number": 85,
                    "line_number": 1,
                    "text": "وَٱلَّذِينَ",
                    "translation": {
                        "text": "And those who",
                        "language_name": "english"
                    }
                },
                {
                    "id": 39567,
                    "position": 2,
                    "char_type_name": "word",
                    "v1_page": 85,
                    "text_uthmani": "يُنفِقُونَ",
                    "text_indopak": "يُنۡفِقُوۡنَ",
                    "code_v1": "ﭒ",
                    "page_number": 85,
                    "line_number": 1,
                    "text": "يُنفِقُونَ",
                    "translation": {
                        "text": "spend",
                        "language_name": "english"
                    }
                },
                {
                    "id": 39568,
                    "position": 3,
                    "char_type_name": "word",
                    "v1_page": 85,
                    "text_uthmani": "أَمْوَٰلَهُمْ",
                    "text_indopak": "اَمۡوَالَهُمۡ",
                    "code_v1": "ﭓ",
                    "page_number": 85,
                    "line_number": 1,
                    "text": "أَمْوَٰلَهُمْ",
                    "translation": {
                        "text": "their wealth",
                        "language_name": "english"
                    }
                },
                {
                    "id": 39569,
                    "position": 4,
                    "char_type_name": "word",
                    "v1_page": 85,
                    "text_uthmani": "رِئَآءَ",
                    "text_indopak": "رِئَآءَ",
                    "code_v1": "ﭔ",
                    "page_number": 85,
                    "line_number": 1,
                    "text": "رِئَآءَ",
                    "translation": {
                        "text": "to be seen",
                        "language_name": "english"
                    }
                },
                {
                    "id": 39570,
                    "position": 5,
                    "char_type_name": "word",
                    "v1_page": 85,
                    "text_uthmani": "ٱلنَّاسِ",
                    "text_indopak": "النَّاسِ",
                    "code_v1": "ﭕ",
                    "page_number": 85,
                    "line_number": 1,
                    "text": "ٱلنَّاسِ",
                    "translation": {
                        "text": "(by) the people",
                        "language_name": "english"
                    }
                },
                {
                    "id": 39571,
                    "position": 6,
                    "char_type_name": "word",
                    "v1_page": 85,
                    "text_uthmani": "وَلَا",
                    "text_indopak": "وَلَا",
                    "code_v1": "ﭖ",
                    "page_number": 85,
                    "line_number": 1,
                    "text": "وَلَا",
                    "translation": {
                        "text": "and not",
                        "language_name": "english"
                    }
                },
                {
                    "id": 39572,
                    "position": 7,
                    "char_type_name": "word",
                    "v1_page": 85,
                    "text_uthmani": "يُؤْمِنُونَ",
                    "text_indopak": "يُؤۡمِنُوۡنَ",
                    "code_v1": "ﭗ",
                    "page_number": 85,
                    "line_number": 1,
                    "text": "يُؤْمِنُونَ",
                    "translation": {
                        "text": "they believe",
                        "language_name": "english"
                    }
                },
                {
                    "id": 39573,
                    "position": 8,
                    "char_type_name": "word",
                    "v1_page": 85,
                    "text_uthmani": "بِٱللَّهِ",
                    "text_indopak": "بِاللّٰهِ",
                    "code_v1": "ﭘ",
                    "page_number": 85,
                    "line_number": 2,
                    "text": "بِٱللَّهِ",
                    "translation": {
                        "text": "in Allah",
                        "language_name": "english"
                    }
                },
                {
                    "id": 39574,
                    "position": 9,
                    "char_type_name": "word",
                    "v1_page": 85,
                    "text_uthmani": "وَلَا",
                    "text_indopak": "وَلَا",
                    "code_v1": "ﭙ",
                    "page_number": 85,
                    "line_number": 2,
                    "text": "وَلَا",
                    "translation": {
                        "text": "and not",
                        "language_name": "english"
                    }
                },
                {
                    "id": 39575,
                    "position": 10,
                    "char_type_name": "word",
                    "v1_page": 85,
                    "text_uthmani": "بِٱلْيَوْمِ",
                    "text_indopak": "بِالۡيَوۡمِ",
                    "code_v1": "ﭚ",
                    "page_number": 85,
                    "line_number": 2,
                    "text": "بِٱلْيَوْمِ",
                    "translation": {
                        "text": "in the Day",
                        "language_name": "english"
                    }
                },
                {
                    "id": 39576,
                    "position": 11,
                    "char_type_name": "word",
                    "v1_page": 85,
                    "text_uthmani": "ٱلْـَٔاخِرِ ۗ",
                    "text_indopak": "الۡاٰخِرِ​ؕ",
                    "code_v1": "ﭛﭜ",
                    "page_number": 85,
                    "line_number": 2,
                    "text": "ٱلْـَٔاخِرِ ۗ",
                    "translation": {
                        "text": "the Last",
                        "language_name": "english"
                    }
                },
                {
                    "id": 39578,
                    "position": 12,
                    "char_type_name": "word",
                    "v1_page": 85,
                    "text_uthmani": "وَمَن",
                    "text_indopak": "وَمَنۡ",
                    "code_v1": "ﭝ",
                    "page_number": 85,
                    "line_number": 2,
                    "text": "وَمَن",
                    "translation": {
                        "text": "and whoever",
                        "language_name": "english"
                    }
                },
                {
                    "id": 39579,
                    "position": 13,
                    "char_type_name": "word",
                    "v1_page": 85,
                    "text_uthmani": "يَكُنِ",
                    "text_indopak": "يَّكُنِ",
                    "code_v1": "ﭞ",
                    "page_number": 85,
                    "line_number": 2,
                    "text": "يَكُنِ",
                    "translation": {
                        "text": "has",
                        "language_name": "english"
                    }
                },
                {
                    "id": 39580,
                    "position": 14,
                    "char_type_name": "word",
                    "v1_page": 85,
                    "text_uthmani": "ٱلشَّيْطَـٰنُ",
                    "text_indopak": "الشَّيۡطٰنُ",
                    "code_v1": "ﭟ",
                    "page_number": 85,
                    "line_number": 2,
                    "text": "ٱلشَّيْطَـٰنُ",
                    "translation": {
                        "text": "the Shaitaan",
                        "language_name": "english"
                    }
                },
                {
                    "id": 39581,
                    "position": 15,
                    "char_type_name": "word",
                    "v1_page": 85,
                    "text_uthmani": "لَهُۥ",
                    "text_indopak": "لَهٗ",
                    "code_v1": "ﭠ",
                    "page_number": 85,
                    "line_number": 2,
                    "text": "لَهُۥ",
                    "translation": {
                        "text": "for him",
                        "language_name": "english"
                    }
                },
                {
                    "id": 39582,
                    "position": 16,
                    "char_type_name": "word",
                    "v1_page": 85,
                    "text_uthmani": "قَرِينًۭا",
                    "text_indopak": "قَرِيۡنًا",
                    "code_v1": "ﭡ",
                    "page_number": 85,
                    "line_number": 2,
                    "text": "قَرِينًۭا",
                    "translation": {
                        "text": "(as) companion ",
                        "language_name": "english"
                    }
                },
                {
                    "id": 39583,
                    "position": 17,
                    "char_type_name": "word",
                    "v1_page": 85,
                    "text_uthmani": "فَسَآءَ",
                    "text_indopak": "فَسَآءَ",
                    "code_v1": "ﭢ",
                    "page_number": 85,
                    "line_number": 2,
                    "text": "فَسَآءَ",
                    "translation": {
                        "text": "then evil",
                        "language_name": "english"
                    }
                },
                {
                    "id": 39584,
                    "position": 18,
                    "char_type_name": "word",
                    "v1_page": 85,
                    "text_uthmani": "قَرِينًۭا",
                    "text_indopak": "قَرِيۡنًا‏",
                    "code_v1": "ﭣ",
                    "page_number": 85,
                    "line_number": 3,
                    "text": "قَرِينًۭا",
                    "translation": {
                        "text": "(is he as) a companion",
                        "language_name": "english"
                    }
                },
                {
                    "id": 39585,
                    "position": 19,
                    "char_type_name": "end",
                    "v1_page": 85,
                    "text_uthmani": "٣٨",
                    "text_indopak": "٣٨",
                    "code_v1": "ﭤ",
                    "page_number": 85,
                    "line_number": 3,
                    "text": "٣٨",
                    "translation": {
                        "text": "(38)",
                        "language_name": "english"
                    }
                }
            ]
        },
        {
            "id": 532,
            "verse_number": 39,
            "verse_key": "4:39",
            "hizb_number": 9,
            "rub_el_hizb_number": 34,
            "ruku_number": 67,
            "manzil_number": 1,
            "sajdah_number": null,
            "text_uthmani_simple": "وماذا عليهم لو ءامنوا۟ بالله واليوم الءاخر وانفقوا۟ مما رزقهم الله وكان الله بهم عليما",
            "text_uthmani": "وَمَاذَا عَلَيْهِمْ لَوْ ءَامَنُوا۟ بِٱللَّهِ وَٱلْيَوْمِ ٱلْـَٔاخِرِ وَأَنفَقُوا۟ مِمَّا رَزَقَهُمُ ٱللَّهُ ۚ وَكَانَ ٱللَّهُ بِهِمْ عَلِيمًا",
            "page_number": 85,
            "juz_number": 5,
            "words": [
                {
                    "id": 40381,
                    "position": 1,
                    "char_type_name": "word",
                    "v1_page": 85,
                    "text_uthmani": "وَمَاذَا",
                    "text_indopak": "وَمَاذَا",
                    "code_v1": "ﭥ",
                    "page_number": 85,
                    "line_number": 3,
                    "text": "وَمَاذَا",
                    "translation": {
                        "text": "And what",
                        "language_name": "english"
                    }
                },
                {
                    "id": 40382,
                    "position": 2,
                    "char_type_name": "word",
                    "v1_page": 85,
                    "text_uthmani": "عَلَيْهِمْ",
                    "text_indopak": "عَلَيۡهِمۡ",
                    "code_v1": "ﭦ",
                    "page_number": 85,
                    "line_number": 3,
                    "text": "عَلَيْهِمْ",
                    "translation": {
                        "text": "(is) against them",
                        "language_name": "english"
                    }
                },
                {
                    "id": 40383,
                    "position": 3,
                    "char_type_name": "word",
                    "v1_page": 85,
                    "text_uthmani": "لَوْ",
                    "text_indopak": "لَوۡ",
                    "code_v1": "ﭧ",
                    "page_number": 85,
                    "line_number": 3,
                    "text": "لَوْ",
                    "translation": {
                        "text": "if",
                        "language_name": "english"
                    }
                },
                {
                    "id": 40384,
                    "position": 4,
                    "char_type_name": "word",
                    "v1_page": 85,
                    "text_uthmani": "ءَامَنُوا۟",
                    "text_indopak": "اٰمَنُوۡا",
                    "code_v1": "ﭨ",
                    "page_number": 85,
                    "line_number": 3,
                    "text": "ءَامَنُوا۟",
                    "translation": {
                        "text": "they believed",
                        "language_name": "english"
                    }
                },
                {
                    "id": 40385,
                    "position": 5,
                    "char_type_name": "word",
                    "v1_page": 85,
                    "text_uthmani": "بِٱللَّهِ",
                    "text_indopak": "بِاللّٰهِ",
                    "code_v1": "ﭩ",
                    "page_number": 85,
                    "line_number": 3,
                    "text": "بِٱللَّهِ",
                    "translation": {
                        "text": "in Allah",
                        "language_name": "english"
                    }
                },
                {
                    "id": 40386,
                    "position": 6,
                    "char_type_name": "word",
                    "v1_page": 85,
                    "text_uthmani": "وَٱلْيَوْمِ",
                    "text_indopak": "وَالۡيَوۡمِ",
                    "code_v1": "ﭪ",
                    "page_number": 85,
                    "line_number": 3,
                    "text": "وَٱلْيَوْمِ",
                    "translation": {
                        "text": "and the Day",
                        "language_name": "english"
                    }
                },
                {
                    "id": 40387,
                    "position": 7,
                    "char_type_name": "word",
                    "v1_page": 85,
                    "text_uthmani": "ٱلْـَٔاخِرِ",
                    "text_indopak": "الۡاٰخِرِ",
                    "code_v1": "ﭫ",
                    "page_number": 85,
                    "line_number": 3,
                    "text": "ٱلْـَٔاخِرِ",
                    "translation": {
                        "text": "the Last",
                        "language_name": "english"
                    }
                },
                {
                    "id": 40388,
                    "position": 8,
                    "char_type_name": "word",
                    "v1_page": 85,
                    "text_uthmani": "وَأَنفَقُوا۟",
                    "text_indopak": "وَاَنۡفَقُوۡا",
                    "code_v1": "ﭬ",
                    "page_number": 85,
                    "line_number": 3,
                    "text": "وَأَنفَقُوا۟",
                    "translation": {
                        "text": "and spent",
                        "language_name": "english"
                    }
                },
                {
                    "id": 40389,
                    "position": 9,
                    "char_type_name": "word",
                    "v1_page": 85,
                    "text_uthmani": "مِمَّا",
                    "text_indopak": "مِمَّا",
                    "code_v1": "ﭭ",
                    "page_number": 85,
                    "line_number": 4,
                    "text": "مِمَّا",
                    "translation": {
                        "text": "from what",
                        "language_name": "english"
                    }
                },
                {
                    "id": 40390,
                    "position": 10,
                    "char_type_name": "word",
                    "v1_page": 85,
                    "text_uthmani": "رَزَقَهُمُ",
                    "text_indopak": "رَزَقَهُمُ",
                    "code_v1": "ﭮ",
                    "page_number": 85,
                    "line_number": 4,
                    "text": "رَزَقَهُمُ",
                    "translation": {
                        "text": "(has) provided them",
                        "language_name": "english"
                    }
                },
                {
                    "id": 40391,
                    "position": 11,
                    "char_type_name": "word",
                    "v1_page": 85,
                    "text_uthmani": "ٱللَّهُ ۚ",
                    "text_indopak": "اللّٰهُ​ ؕ",
                    "code_v1": "ﭯﭰ",
                    "page_number": 85,
                    "line_number": 4,
                    "text": "ٱللَّهُ ۚ",
                    "translation": {
                        "text": "Allah",
                        "language_name": "english"
                    }
                },
                {
                    "id": 40393,
                    "position": 12,
                    "char_type_name": "word",
                    "v1_page": 85,
                    "text_uthmani": "وَكَانَ",
                    "text_indopak": "وَكَانَ",
                    "code_v1": "ﭱ",
                    "page_number": 85,
                    "line_number": 4,
                    "text": "وَكَانَ",
                    "translation": {
                        "text": "And is",
                        "language_name": "english"
                    }
                },
                {
                    "id": 40394,
                    "position": 13,
                    "char_type_name": "word",
                    "v1_page": 85,
                    "text_uthmani": "ٱللَّهُ",
                    "text_indopak": "اللّٰهُ",
                    "code_v1": "ﭲ",
                    "page_number": 85,
                    "line_number": 4,
                    "text": "ٱللَّهُ",
                    "translation": {
                        "text": "Allah",
                        "language_name": "english"
                    }
                },
                {
                    "id": 40395,
                    "position": 14,
                    "char_type_name": "word",
                    "v1_page": 85,
                    "text_uthmani": "بِهِمْ",
                    "text_indopak": "بِهِمۡ",
                    "code_v1": "ﭳ",
                    "page_number": 85,
                    "line_number": 4,
                    "text": "بِهِمْ",
                    "translation": {
                        "text": "about them",
                        "language_name": "english"
                    }
                },
                {
                    "id": 40396,
                    "position": 15,
                    "char_type_name": "word",
                    "v1_page": 85,
                    "text_uthmani": "عَلِيمًا",
                    "text_indopak": "عَلِيۡمًا‏",
                    "code_v1": "ﭴ",
                    "page_number": 85,
                    "line_number": 4,
                    "text": "عَلِيمًا",
                    "translation": {
                        "text": "All-Knower",
                        "language_name": "english"
                    }
                },
                {
                    "id": 40397,
                    "position": 16,
                    "char_type_name": "end",
                    "v1_page": 85,
                    "text_uthmani": "٣٩",
                    "text_indopak": "٣٩",
                    "code_v1": "ﭵ",
                    "page_number": 85,
                    "line_number": 4,
                    "text": "٣٩",
                    "translation": {
                        "text": "(39)",
                        "language_name": "english"
                    }
                }
            ]
        },
        {
            "id": 533,
            "verse_number": 40,
            "verse_key": "4:40",
            "hizb_number": 9,
            "rub_el_hizb_number": 34,
            "ruku_number": 67,
            "manzil_number": 1,
            "sajdah_number": null,
            "text_uthmani_simple": "ان الله لا يظلم مثقال ذرة وان تك حسنة يضعفها ويؤت من لدنه اجرا عظيما",
            "text_uthmani": "إِنَّ ٱللَّهَ لَا يَظْلِمُ مِثْقَالَ ذَرَّةٍ ۖ وَإِن تَكُ حَسَنَةً يُضَـٰعِفْهَا وَيُؤْتِ مِن لَّدُنْهُ أَجْرًا عَظِيمًا",
            "page_number": 85,
            "juz_number": 5,
            "words": [
                {
                    "id": 41120,
                    "position": 1,
                    "char_type_name": "word",
                    "v1_page": 85,
                    "text_uthmani": "إِنَّ",
                    "text_indopak": "اِنَّ",
                    "code_v1": "ﭶ",
                    "page_number": 85,
                    "line_number": 4,
                    "text": "إِنَّ",
                    "translation": {
                        "text": "Indeed",
                        "language_name": "english"
                    }
                },
                {
                    "id": 41121,
                    "position": 2,
                    "char_type_name": "word",
                    "v1_page": 85,
                    "text_uthmani": "ٱللَّهَ",
                    "text_indopak": "اللّٰهَ",
                    "code_v1": "ﭷ",
                    "page_number": 85,
                    "line_number": 4,
                    "text": "ٱللَّهَ",
                    "translation": {
                        "text": "Allah",
                        "language_name": "english"
                    }
                },
                {
                    "id": 41122,
                    "position": 3,
                    "char_type_name": "word",
                    "v1_page": 85,
                    "text_uthmani": "لَا",
                    "text_indopak": "لَا",
                    "code_v1": "ﭸ",
                    "page_number": 85,
                    "line_number": 4,
                    "text": "لَا",
                    "translation": {
                        "text": "(does) not",
                        "language_name": "english"
                    }
                },
                {
                    "id": 41123,
                    "position": 4,
                    "char_type_name": "word",
                    "v1_page": 85,
                    "text_uthmani": "يَظْلِمُ",
                    "text_indopak": "يَظۡلِمُ",
                    "code_v1": "ﭹ",
                    "page_number": 85,
                    "line_number": 4,
                    "text": "يَظْلِمُ",
                    "translation": {
                        "text": "wrong",
                        "language_name": "english"
                    }
                },
                {
                    "id": 41124,
                    "position": 5,
                    "char_type_name": "word",
                    "v1_page": 85,
                    "text_uthmani": "مِثْقَالَ",
                    "text_indopak": "مِثۡقَالَ",
                    "code_v1": "ﭺ",
                    "page_number": 85,
                    "line_number": 5,
                    "text": "مِثْقَالَ",
                    "translation": {
                        "text": "(as much as) weight",
                        "language_name": "english"
                    }
                },
                {
                    "id": 41125,
                    "position": 6,
                    "char_type_name": "word",
                    "v1_page": 85,
                    "text_uthmani": "ذَرَّةٍۢ ۖ",
                    "text_indopak": "ذَرَّةٍ​ ۚ",
                    "code_v1": "ﭻﭼ",
                    "page_number": 85,
                    "line_number": 5,
                    "text": "ذَرَّةٍۢ ۖ",
                    "translation": {
                        "text": "(of) an atom",
                        "language_name": "english"
                    }
                },
                {
                    "id": 41127,
                    "position": 7,
                    "char_type_name": "word",
                    "v1_page": 85,
                    "text_uthmani": "وَإِن",
                    "text_indopak": "وَاِنۡ",
                    "code_v1": "ﭽ",
                    "page_number": 85,
                    "line_number": 5,
                    "text": "وَإِن",
                    "translation": {
                        "text": "And if",
                        "language_name": "english"
                    }
                },
                {
                    "id": 41128,
                    "position": 8,
                    "char_type_name": "word",
                    "v1_page": 85,
                    "text_uthmani": "تَكُ",
                    "text_indopak": "تَكُ",
                    "code_v1": "ﭾ",
                    "page_number": 85,
                    "line_number": 5,
                    "text": "تَكُ",
                    "translation": {
                        "text": "there is",
                        "language_name": "english"
                    }
                },
                {
                    "id": 41129,
                    "position": 9,
                    "char_type_name": "word",
                    "v1_page": 85,
                    "text_uthmani": "حَسَنَةًۭ",
                    "text_indopak": "حَسَنَةً",
                    "code_v1": "ﭿ",
                    "page_number": 85,
                    "line_number": 5,
                    "text": "حَسَنَةًۭ",
                    "translation": {
                        "text": "a good",
                        "language_name": "english"
                    }
                },
                {
                    "id": 41130,
                    "position": 10,
                    "char_type_name": "word",
                    "v1_page": 85,
                    "text_uthmani": "يُضَـٰعِفْهَا",
                    "text_indopak": "يُّضٰعِفۡهَا",
                    "code_v1": "ﮀ",
                    "page_number": 85,
                    "line_number": 5,
                    "text": "يُضَـٰعِفْهَا",
                    "translation": {
                        "text": "He doubles it",
                        "language_name": "english"
                    }
                },
                {
                    "id": 41131,
                    "position": 11,
                    "char_type_name": "word",
                    "v1_page": 85,
                    "text_uthmani": "وَيُؤْتِ",
                    "text_indopak": "وَيُؤۡتِ",
                    "code_v1": "ﮁ",
                    "page_number": 85,
                    "line_number": 5,
                    "text": "وَيُؤْتِ",
                    "translation": {
                        "text": "and gives",
                        "language_name": "english"
                    }
                },
                {
                    "id": 41132,
                    "position": 12,
                    "char_type_name": "word",
                    "v1_page": 85,
                    "text_uthmani": "مِن",
                    "text_indopak": "مِنۡ",
                    "code_v1": "ﮂ",
                    "page_number": 85,
                    "line_number": 5,
                    "text": "مِن",
                    "translation": {
                        "text": "from",
                        "language_name": "english"
                    }
                },
                {
                    "id": 41133,
                    "position": 13,
                    "char_type_name": "word",
                    "v1_page": 85,
                    "text_uthmani": "لَّدُنْهُ",
                    "text_indopak": "لَّدُنۡهُ",
                    "code_v1": "ﮃ",
                    "page_number": 85,
                    "line_number": 5,
                    "text": "لَّدُنْهُ",
                    "translation": {
                        "text": "near Him",
                        "language_name": "english"
                    }
                },
                {
                    "id": 41134,
                    "position": 14,
                    "char_type_name": "word",
                    "v1_page": 85,
                    "text_uthmani": "أَجْرًا",
                    "text_indopak": "اَجۡرًا",
                    "code_v1": "ﮄ",
                    "page_number": 85,
                    "line_number": 6,
                    "text": "أَجْرًا",
                    "translation": {
                        "text": "a reward",
                        "language_name": "english"
                    }
                },
                {
                    "id": 41135,
                    "position": 15,
                    "char_type_name": "word",
                    "v1_page": 85,
                    "text_uthmani": "عَظِيمًۭا",
                    "text_indopak": "عَظِيۡمًا‏",
                    "code_v1": "ﮅ",
                    "page_number": 85,
                    "line_number": 6,
                    "text": "عَظِيمًۭا",
                    "translation": {
                        "text": "great",
                        "language_name": "english"
                    }
                },
                {
                    "id": 41136,
                    "position": 16,
                    "char_type_name": "end",
                    "v1_page": 85,
                    "text_uthmani": "٤٠",
                    "text_indopak": "٤٠",
                    "code_v1": "ﮆ",
                    "page_number": 85,
                    "line_number": 6,
                    "text": "٤٠",
                    "translation": {
                        "text": "(40)",
                        "language_name": "english"
                    }
                }
            ]
        },
        {
            "id": 534,
            "verse_number": 41,
            "verse_key": "4:41",
            "hizb_number": 9,
            "rub_el_hizb_number": 34,
            "ruku_number": 67,
            "manzil_number": 1,
            "sajdah_number": null,
            "text_uthmani_simple": "فكيف اذا جئنا من كل امةۭ بشهيد وجئنا بك على هؤلاء شهيدا",
            "text_uthmani": "فَكَيْفَ إِذَا جِئْنَا مِن كُلِّ أُمَّةٍۭ بِشَهِيدٍ وَجِئْنَا بِكَ عَلَىٰ هَـٰٓؤُلَآءِ شَهِيدًا",
            "page_number": 85,
            "juz_number": 5,
            "words": [
                {
                    "id": 42009,
                    "position": 1,
                    "char_type_name": "word",
                    "v1_page": 85,
                    "text_uthmani": "فَكَيْفَ",
                    "text_indopak": "فَكَيۡـفَ",
                    "code_v1": "ﮇ",
                    "page_number": 85,
                    "line_number": 6,
                    "text": "فَكَيْفَ",
                    "translation": {
                        "text": "So how (will it be)",
                        "language_name": "english"
                    }
                },
                {
                    "id": 42010,
                    "position": 2,
                    "char_type_name": "word",
                    "v1_page": 85,
                    "text_uthmani": "إِذَا",
                    "text_indopak": "اِذَا",
                    "code_v1": "ﮈ",
                    "page_number": 85,
                    "line_number": 6,
                    "text": "إِذَا",
                    "translation": {
                        "text": "when",
                        "language_name": "english"
                    }
                },
                {
                    "id": 42011,
                    "position": 3,
                    "char_type_name": "word",
                    "v1_page": 85,
                    "text_uthmani": "جِئْنَا",
                    "text_indopak": "جِئۡـنَا",
                    "code_v1": "ﮉ",
                    "page_number": 85,
                    "line_number": 6,
                    "text": "جِئْنَا",
                    "translation": {
                        "text": "We bring",
                        "language_name": "english"
                    }
                },
                {
                    "id": 42012,
                    "position": 4,
                    "char_type_name": "word",
                    "v1_page": 85,
                    "text_uthmani": "مِن",
                    "text_indopak": "مِنۡ",
                    "code_v1": "ﮊ",
                    "page_number": 85,
                    "line_number": 6,
                    "text": "مِن",
                    "translation": {
                        "text": "from",
                        "language_name": "english"
                    }
                },
                {
                    "id": 42013,
                    "position": 5,
                    "char_type_name": "word",
                    "v1_page": 85,
                    "text_uthmani": "كُلِّ",
                    "text_indopak": "كُلِّ",
                    "code_v1": "ﮋ",
                    "page_number": 85,
                    "line_number": 6,
                    "text": "كُلِّ",
                    "translation": {
                        "text": "every",
                        "language_name": "english"
                    }
                },
                {
                    "id": 42014,
                    "position": 6,
                    "char_type_name": "word",
                    "v1_page": 85,
                    "text_uthmani": "أُمَّةٍۭ",
                    "text_indopak": "اُمَّةٍ ۭ",
                    "code_v1": "ﮌ",
                    "page_number": 85,
                    "line_number": 6,
                    "text": "أُمَّةٍۭ",
                    "translation": {
                        "text": "nation",
                        "language_name": "english"
                    }
                },
                {
                    "id": 42015,
                    "position": 7,
                    "char_type_name": "word",
                    "v1_page": 85,
                    "text_uthmani": "بِشَهِيدٍۢ",
                    "text_indopak": "بِشَهِيۡدٍ",
                    "code_v1": "ﮍ",
                    "page_number": 85,
                    "line_number": 6,
                    "text": "بِشَهِيدٍۢ",
                    "translation": {
                        "text": "a witness",
                        "language_name": "english"
                    }
                },
                {
                    "id": 42016,
                    "position": 8,
                    "char_type_name": "word",
                    "v1_page": 85,
                    "text_uthmani": "وَجِئْنَا",
                    "text_indopak": "وَّجِئۡـنَا",
                    "code_v1": "ﮎ",
                    "page_number": 85,
                    "line_number": 7,
                    "text": "وَجِئْنَا",
                    "translation": {
                        "text": "and We bring",
                        "language_name": "english"
                    }
                },
                {
                    "id": 42017,
                    "position": 9,
                    "char_type_name": "word",
                    "v1_page": 85,
                    "text_uthmani": "بِكَ",
                    "text_indopak": "بِكَ",
                    "code_v1": "ﮏ",
                    "page_number": 85,
                    "line_number": 7,
                    "text": "بِكَ",
                    "translation": {
                        "text": "you",
                        "language_name": "english"
                    }
                },
                {
                    "id": 42018,
                    "position": 10,
                    "char_type_name": "word",
                    "v1_page": 85,
                    "text_uthmani": "عَلَىٰ",
                    "text_indopak": "عَلٰى",
                    "code_v1": "ﮐ",
                    "page_number": 85,
                    "line_number": 7,
                    "text": "عَلَىٰ",
                    "translation": {
                        "text": "against",
                        "language_name": "english"
                    }
                },
                {
                    "id": 42019,
                    "position": 11,
                    "char_type_name": "word",
                    "v1_page": 85,
                    "text_uthmani": "هَـٰٓؤُلَآءِ",
                    "text_indopak": "هٰٓؤُلَاۤءِ",
                    "code_v1": "ﮑ",
                    "page_number": 85,
                    "line_number": 7,
                    "text": "هَـٰٓؤُلَآءِ",
                    "translation": {
                        "text": "these (people)",
                        "language_name": "english"
                    }
                },
                {
                    "id": 42020,
                    "position": 12,
                    "char_type_name": "word",
                    "v1_page": 85,
                    "text_uthmani": "شَهِيدًۭا",
                    "text_indopak": "شَهِيۡدًا ؕ‏",
                    "code_v1": "ﮒ",
                    "page_number": 85,
                    "line_number": 7,
                    "text": "شَهِيدًۭا",
                    "translation": {
                        "text": "(as) a witness",
                        "language_name": "english"
                    }
                },
                {
                    "id": 42021,
                    "position": 13,
                    "char_type_name": "end",
                    "v1_page": 85,
                    "text_uthmani": "٤١",
                    "text_indopak": "٤١",
                    "code_v1": "ﮓ",
                    "page_number": 85,
                    "line_number": 7,
                    "text": "٤١",
                    "translation": {
                        "text": "(41)",
                        "language_name": "english"
                    }
                }
            ]
        },
        {
            "id": 535,
            "verse_number": 42,
            "verse_key": "4:42",
            "hizb_number": 9,
            "rub_el_hizb_number": 34,
            "ruku_number": 67,
            "manzil_number": 1,
            "sajdah_number": null,
            "text_uthmani_simple": "يومئذ يود الذين كفروا۟ وعصوا۟ الرسول لو تسوى بهم الارض ولا يكتمون الله حديثا",
            "text_uthmani": "يَوْمَئِذٍ يَوَدُّ ٱلَّذِينَ كَفَرُوا۟ وَعَصَوُا۟ ٱلرَّسُولَ لَوْ تُسَوَّىٰ بِهِمُ ٱلْأَرْضُ وَلَا يَكْتُمُونَ ٱللَّهَ حَدِيثًا",
            "page_number": 85,
            "juz_number": 5,
            "words": [
                {
                    "id": 42747,
                    "position": 1,
                    "char_type_name": "word",
                    "v1_page": 85,
                    "text_uthmani": "يَوْمَئِذٍۢ",
                    "text_indopak": "يَوۡمَٮِٕذٍ",
                    "code_v1": "ﮔ",
                    "page_number": 85,
                    "line_number": 7,
                    "text": "يَوْمَئِذٍۢ",
                    "translation": {
                        "text": "(On) that Day",
                        "language_name": "english"
                    }
                },
                {
                    "id": 42748,
                    "position": 2,
                    "char_type_name": "word",
                    "v1_page": 85,
                    "text_uthmani": "يَوَدُّ",
                    "text_indopak": "يَّوَدُّ",
                    "code_v1": "ﮕ",
                    "page_number": 85,
                    "line_number": 7,
                    "text": "يَوَدُّ",
                    "translation": {
                        "text": "will wish",
                        "language_name": "english"
                    }
                },
                {
                    "id": 42749,
                    "position": 3,
                    "char_type_name": "word",
                    "v1_page": 85,
                    "text_uthmani": "ٱلَّذِينَ",
                    "text_indopak": "الَّذِيۡنَ",
                    "code_v1": "ﮖ",
                    "page_number": 85,
                    "line_number": 7,
                    "text": "ٱلَّذِينَ",
                    "translation": {
                        "text": "those who",
                        "language_name": "english"
                    }
                },
                {
                    "id": 42750,
                    "position": 4,
                    "char_type_name": "word",
                    "v1_page": 85,
                    "text_uthmani": "كَفَرُوا۟",
                    "text_indopak": "كَفَرُوۡا",
                    "code_v1": "ﮗ",
                    "page_number": 85,
                    "line_number": 8,
                    "text": "كَفَرُوا۟",
                    "translation": {
                        "text": "disbelieved",
                        "language_name": "english"
                    }
                },
                {
                    "id": 42751,
                    "position": 5,
                    "char_type_name": "word",
                    "v1_page": 85,
                    "text_uthmani": "وَعَصَوُا۟",
                    "text_indopak": "وَعَصَوُا",
                    "code_v1": "ﮘ",
                    "page_number": 85,
                    "line_number": 8,
                    "text": "وَعَصَوُا۟",
                    "translation": {
                        "text": "and disobeyed",
                        "language_name": "english"
                    }
                },
                {
                    "id": 42752,
                    "position": 6,
                    "char_type_name": "word",
                    "v1_page": 85,
                    "text_uthmani": "ٱلرَّسُولَ",
                    "text_indopak": "الرَّسُوۡلَ",
                    "code_v1": "ﮙ",
                    "page_number": 85,
                    "line_number": 8,
                    "text": "ٱلرَّسُولَ",
                    "translation": {
                        "text": "the Messenger",
                        "language_name": "english"
                    }
                },
                {
                    "id": 42753,
                    "position": 7,
                    "char_type_name": "word",
                    "v1_page": 85,
                    "text_uthmani": "لَوْ",
                    "text_indopak": "لَوۡ",
                    "code_v1": "ﮚ",
                    "page_number": 85,
                    "line_number": 8,
                    "text": "لَوْ",
                    "translation": {
                        "text": "if",
                        "language_name": "english"
                    }
                },
                {
                    "id": 42754,
                    "position": 8,
                    "char_type_name": "word",
                    "v1_page": 85,
                    "text_uthmani": "تُسَوَّىٰ",
                    "text_indopak": "تُسَوّٰى",
                    "code_v1": "ﮛ",
                    "page_number": 85,
                    "line_number": 8,
                    "text": "تُسَوَّىٰ",
                    "translation": {
                        "text": "was leveled",
                        "language_name": "english"
                    }
                },
                {
                    "id": 42755,
                    "position": 9,
                    "char_type_name": "word",
                    "v1_page": 85,
                    "text_uthmani": "بِهِمُ",
                    "text_indopak": "بِهِمُ",
                    "code_v1": "ﮜ",
                    "page_number": 85,
                    "line_number": 8,
                    "text": "بِهِمُ",
                    "translation": {
                        "text": "with them",
                        "language_name": "english"
                    }
                },
                {
                    "id": 42756,
                    "position": 10,
                    "char_type_name": "word",
                    "v1_page": 85,
                    "text_uthmani": "ٱلْأَرْضُ",
                    "text_indopak": "الۡاَرۡضُ ؕ",
                    "code_v1": "ﮝ",
                    "page_number": 85,
                    "line_number": 8,
                    "text": "ٱلْأَرْضُ",
                    "translation": {
                        "text": "the earth",
                        "language_name": "english"
                    }
                },
                {
                    "id": 42757,
                    "position": 11,
                    "char_type_name": "word",
                    "v1_page": 85,
                    "text_uthmani": "وَلَا",
                    "text_indopak": "وَلَا",
                    "code_v1": "ﮞ",
                    "page_number": 85,
                    "line_number": 8,
                    "text": "وَلَا",
                    "translation": {
                        "text": "and not",
                        "language_name": "english"
                    }
                },
                {
                    "id": 42758,
                    "position": 12,
                    "char_type_name": "word",
                    "v1_page": 85,
                    "text_uthmani": "يَكْتُمُونَ",
                    "text_indopak": "يَكۡتُمُوۡنَ",
                    "code_v1": "ﮟ",
                    "page_number": 85,
                    "line_number": 8,
                    "text": "يَكْتُمُونَ",
                    "translation": {
                        "text": "they will (be able to) hide",
                        "language_name": "english"
                    }
                },
                {
                    "id": 42759,
                    "position": 13,
                    "char_type_name": "word",
                    "v1_page": 85,
                    "text_uthmani": "ٱللَّهَ",
                    "text_indopak": "اللّٰهَ",
                    "code_v1": "ﮠ",
                    "page_number": 85,
                    "line_number": 9,
                    "text": "ٱللَّهَ",
                    "translation": {
                        "text": "(from) Allah",
                        "language_name": "english"
                    }
                },
                {
                    "id": 42760,
                    "position": 14,
                    "char_type_name": "word",
                    "v1_page": 85,
                    "text_uthmani": "حَدِيثًۭا",
                    "text_indopak": "حَدِيۡـثًا‏",
                    "code_v1": "ﮡ",
                    "page_number": 85,
                    "line_number": 9,
                    "text": "حَدِيثًۭا",
                    "translation": {
                        "text": "(any) statement",
                        "language_name": "english"
                    }
                },
                {
                    "id": 42761,
                    "position": 15,
                    "char_type_name": "end",
                    "v1_page": 85,
                    "text_uthmani": "٤٢",
                    "text_indopak": "٤٢",
                    "code_v1": "ﮢ",
                    "page_number": 85,
                    "line_number": 9,
                    "text": "٤٢",
                    "translation": {
                        "text": "(42)",
                        "language_name": "english"
                    }
                }
            ]
        },
        {
            "id": 536,
            "verse_number": 43,
            "verse_key": "4:43",
            "hizb_number": 9,
            "rub_el_hizb_number": 34,
            "ruku_number": 68,
            "manzil_number": 1,
            "sajdah_number": null,
            "text_uthmani_simple": "يايها الذين ءامنوا۟ لا تقربوا۟ الصلوة وانتم سكرى حتى تعلموا۟ ما تقولون ولا جنبا الا عابرى سبيل حتى تغتسلوا۟ وان كنتم مرضى او على سفر او جاء احد منكم من الغائط او لمستم النساء فلم تجدوا۟ ماء فتيمموا۟ صعيدا طيبا فامسحوا۟ بوجوهكم وايديكم ان الله كان عفوا غفورا",
            "text_uthmani": "يَـٰٓأَيُّهَا ٱلَّذِينَ ءَامَنُوا۟ لَا تَقْرَبُوا۟ ٱلصَّلَوٰةَ وَأَنتُمْ سُكَـٰرَىٰ حَتَّىٰ تَعْلَمُوا۟ مَا تَقُولُونَ وَلَا جُنُبًا إِلَّا عَابِرِى سَبِيلٍ حَتَّىٰ تَغْتَسِلُوا۟ ۚ وَإِن كُنتُم مَّرْضَىٰٓ أَوْ عَلَىٰ سَفَرٍ أَوْ جَآءَ أَحَدٌ مِّنكُم مِّنَ ٱلْغَآئِطِ أَوْ لَـٰمَسْتُمُ ٱلنِّسَآءَ فَلَمْ تَجِدُوا۟ مَآءً فَتَيَمَّمُوا۟ صَعِيدًا طَيِّبًا فَٱمْسَحُوا۟ بِوُجُوهِكُمْ وَأَيْدِيكُمْ ۗ إِنَّ ٱللَّهَ كَانَ عَفُوًّا غَفُورًا",
            "page_number": 85,
            "juz_number": 5,
            "words": [
                {
                    "id": 43505,
                    "position": 1,
                    "char_type_name": "word",
                    "v1_page": 85,
                    "text_uthmani": "يَـٰٓأَيُّهَا",
                    "text_indopak": "يٰۤـاَيُّهَا",
                    "code_v1": "ﮣ",
                    "page_number": 85,
                    "line_number": 9,
                    "text": "يَـٰٓأَيُّهَا",
                    "translation": {
                        "text": "O you",
                        "language_name": "english"
                    }
                },
                {
                    "id": 43506,
                    "position": 2,
                    "char_type_name": "word",
                    "v1_page": 85,
                    "text_uthmani": "ٱلَّذِينَ",
                    "text_indopak": "الَّذِيۡنَ",
                    "code_v1": "ﮤ",
                    "page_number": 85,
                    "line_number": 9,
                    "text": "ٱلَّذِينَ",
                    "translation": {
                        "text": "who",
                        "language_name": "english"
                    }
                },
                {
                    "id": 43507,
                    "position": 3,
                    "char_type_name": "word",
                    "v1_page": 85,
                    "text_uthmani": "ءَامَنُوا۟",
                    "text_indopak": "اٰمَنُوۡا",
                    "code_v1": "ﮥ",
                    "page_number": 85,
                    "line_number": 9,
                    "text": "ءَامَنُوا۟",
                    "translation": {
                        "text": "believe[d]",
                        "language_name": "english"
                    }
                },
                {
                    "id": 43508,
                    "position": 4,
                    "char_type_name": "word",
                    "v1_page": 85,
                    "text_uthmani": "لَا",
                    "text_indopak": "لَا",
                    "code_v1": "ﮦ",
                    "page_number": 85,
                    "line_number": 9,
                    "text": "لَا",
                    "translation": {
                        "text": "(Do) not",
                        "language_name": "english"
                    }
                },
                {
                    "id": 43509,
                    "position": 5,
                    "char_type_name": "word",
                    "v1_page": 85,
                    "text_uthmani": "تَقْرَبُوا۟",
                    "text_indopak": "تَقۡرَبُوا",
                    "code_v1": "ﮧ",
                    "page_number": 85,
                    "line_number": 9,
                    "text": "تَقْرَبُوا۟",
                    "translation": {
                        "text": "go near",
                        "language_name": "english"
                    }
                },
                {
                    "id": 43510,
                    "position": 6,
                    "char_type_name": "word",
                    "v1_page": 85,
                    "text_uthmani": "ٱلصَّلَوٰةَ",
                    "text_indopak": "الصَّلٰوةَ",
                    "code_v1": "ﮨ",
                    "page_number": 85,
                    "line_number": 9,
                    "text": "ٱلصَّلَوٰةَ",
                    "translation": {
                        "text": "the prayer",
                        "language_name": "english"
                    }
                },
                {
                    "id": 43511,
                    "position": 7,
                    "char_type_name": "word",
                    "v1_page": 85,
                    "text_uthmani": "وَأَنتُمْ",
                    "text_indopak": "وَاَنۡـتُمۡ",
                    "code_v1": "ﮩ",
                    "page_number": 85,
                    "line_number": 10,
                    "text": "وَأَنتُمْ",
                    "translation": {
                        "text": "while you",
                        "language_name": "english"
                    }
                },
                {
                    "id": 43512,
                    "position": 8,
                    "char_type_name": "word",
                    "v1_page": 85,
                    "text_uthmani": "سُكَـٰرَىٰ",
                    "text_indopak": "سُكَارٰى",
                    "code_v1": "ﮪ",
                    "page_number": 85,
                    "line_number": 10,
                    "text": "سُكَـٰرَىٰ",
                    "translation": {
                        "text": "(are) intoxicated",
                        "language_name": "english"
                    }
                },
                {
                    "id": 43513,
                    "position": 9,
                    "char_type_name": "word",
                    "v1_page": 85,
                    "text_uthmani": "حَتَّىٰ",
                    "text_indopak": "حَتّٰى",
                    "code_v1": "ﮫ",
                    "page_number": 85,
                    "line_number": 10,
                    "text": "حَتَّىٰ",
                    "translation": {
                        "text": "until",
                        "language_name": "english"
                    }
                },
                {
                    "id": 43514,
                    "position": 10,
                    "char_type_name": "word",
                    "v1_page": 85,
                    "text_uthmani": "تَعْلَمُوا۟",
                    "text_indopak": "تَعۡلَمُوۡا",
                    "code_v1": "ﮬ",
                    "page_number": 85,
                    "line_number": 10,
                    "text": "تَعْلَمُوا۟",
                    "translation": {
                        "text": "you know",
                        "language_name": "english"
                    }
                },
                {
                    "id": 43515,
                    "position": 11,
                    "char_type_name": "word",
                    "v1_page": 85,
                    "text_uthmani": "مَا",
                    "text_indopak": "مَا",
                    "code_v1": "ﮭ",
                    "page_number": 85,
                    "line_number": 10,
                    "text": "مَا",
                    "translation": {
                        "text": "what",
                        "language_name": "english"
                    }
                },
                {
                    "id": 43516,
                    "position": 12,
                    "char_type_name": "word",
                    "v1_page": 85,
                    "text_uthmani": "تَقُولُونَ",
                    "text_indopak": "تَقُوۡلُوۡنَ",
                    "code_v1": "ﮮ",
                    "page_number": 85,
                    "line_number": 10,
                    "text": "تَقُولُونَ",
                    "translation": {
                        "text": "you are saying",
                        "language_name": "english"
                    }
                },
                {
                    "id": 43517,
                    "position": 13,
                    "char_type_name": "word",
                    "v1_page": 85,
                    "text_uthmani": "وَلَا",
                    "text_indopak": "وَلَا",
                    "code_v1": "ﮯ",
                    "page_number": 85,
                    "line_number": 10,
                    "text": "وَلَا",
                    "translation": {
                        "text": "and not",
                        "language_name": "english"
                    }
                },
                {
                    "id": 43518,
                    "position": 14,
                    "char_type_name": "word",
                    "v1_page": 85,
                    "text_uthmani": "جُنُبًا",
                    "text_indopak": "جُنُبًا",
                    "code_v1": "ﮰ",
                    "page_number": 85,
                    "line_number": 10,
                    "text": "جُنُبًا",
                    "translation": {
                        "text": "(when you are) impure",
                        "language_name": "english"
                    }
                },
                {
                    "id": 43519,
                    "position": 15,
                    "char_type_name": "word",
                    "v1_page": 85,
                    "text_uthmani": "إِلَّا",
                    "text_indopak": "اِلَّا",
                    "code_v1": "ﮱ",
                    "page_number": 85,
                    "line_number": 10,
                    "text": "إِلَّا",
                    "translation": {
                        "text": "except",
                        "language_name": "english"
                    }
                },
                {
                    "id": 43520,
                    "position": 16,
                    "char_type_name": "word",
                    "v1_page": 85,
                    "text_uthmani": "عَابِرِى",
                    "text_indopak": "عَابِرِىۡ",
                    "code_v1": "ﯓ",
                    "page_number": 85,
                    "line_number": 10,
                    "text": "عَابِرِى",
                    "translation": {
                        "text": "(when) passing",
                        "language_name": "english"
                    }
                },
                {
                    "id": 43521,
                    "position": 17,
                    "char_type_name": "word",
                    "v1_page": 85,
                    "text_uthmani": "سَبِيلٍ",
                    "text_indopak": "سَبِيۡلٍ",
                    "code_v1": "ﯔ",
                    "page_number": 85,
                    "line_number": 11,
                    "text": "سَبِيلٍ",
                    "translation": {
                        "text": "(through) a way",
                        "language_name": "english"
                    }
                },
                {
                    "id": 43522,
                    "position": 18,
                    "char_type_name": "word",
                    "v1_page": 85,
                    "text_uthmani": "حَتَّىٰ",
                    "text_indopak": "حَتّٰى",
                    "code_v1": "ﯕ",
                    "page_number": 85,
                    "line_number": 11,
                    "text": "حَتَّىٰ",
                    "translation": {
                        "text": "until",
                        "language_name": "english"
                    }
                },
                {
                    "id": 43523,
                    "position": 19,
                    "char_type_name": "word",
                    "v1_page": 85,
                    "text_uthmani": "تَغْتَسِلُوا۟ ۚ",
                    "text_indopak": "تَغۡتَسِلُوۡا​ ؕ",
                    "code_v1": "ﯖﯗ",
                    "page_number": 85,
                    "line_number": 11,
                    "text": "تَغْتَسِلُوا۟ ۚ",
                    "translation": {
                        "text": "you have bathed",
                        "language_name": "english"
                    }
                },
                {
                    "id": 43525,
                    "position": 20,
                    "char_type_name": "word",
                    "v1_page": 85,
                    "text_uthmani": "وَإِن",
                    "text_indopak": "وَاِنۡ",
                    "code_v1": "ﯘ",
                    "page_number": 85,
                    "line_number": 11,
                    "text": "وَإِن",
                    "translation": {
                        "text": "And if",
                        "language_name": "english"
                    }
                },
                {
                    "id": 43526,
                    "position": 21,
                    "char_type_name": "word",
                    "v1_page": 85,
                    "text_uthmani": "كُنتُم",
                    "text_indopak": "كُنۡتُمۡ",
                    "code_v1": "ﯙ",
                    "page_number": 85,
                    "line_number": 11,
                    "text": "كُنتُم",
                    "translation": {
                        "text": "you are",
                        "language_name": "english"
                    }
                },
                {
                    "id": 43527,
                    "position": 22,
                    "char_type_name": "word",
                    "v1_page": 85,
                    "text_uthmani": "مَّرْضَىٰٓ",
                    "text_indopak": "مَّرۡضٰۤى",
                    "code_v1": "ﯚ",
                    "page_number": 85,
                    "line_number": 11,
                    "text": "مَّرْضَىٰٓ",
                    "translation": {
                        "text": "ill",
                        "language_name": "english"
                    }
                },
                {
                    "id": 43528,
                    "position": 23,
                    "char_type_name": "word",
                    "v1_page": 85,
                    "text_uthmani": "أَوْ",
                    "text_indopak": "اَوۡ",
                    "code_v1": "ﯛ",
                    "page_number": 85,
                    "line_number": 11,
                    "text": "أَوْ",
                    "translation": {
                        "text": "or",
                        "language_name": "english"
                    }
                },
                {
                    "id": 43529,
                    "position": 24,
                    "char_type_name": "word",
                    "v1_page": 85,
                    "text_uthmani": "عَلَىٰ",
                    "text_indopak": "عَلٰى",
                    "code_v1": "ﯜ",
                    "page_number": 85,
                    "line_number": 11,
                    "text": "عَلَىٰ",
                    "translation": {
                        "text": "on",
                        "language_name": "english"
                    }
                },
                {
                    "id": 43530,
                    "position": 25,
                    "char_type_name": "word",
                    "v1_page": 85,
                    "text_uthmani": "سَفَرٍ",
                    "text_indopak": "سَفَرٍ",
                    "code_v1": "ﯝ",
                    "page_number": 85,
                    "line_number": 11,
                    "text": "سَفَرٍ",
                    "translation": {
                        "text": "a journey",
                        "language_name": "english"
                    }
                },
                {
                    "id": 43531,
                    "position": 26,
                    "char_type_name": "word",
                    "v1_page": 85,
                    "text_uthmani": "أَوْ",
                    "text_indopak": "اَوۡ",
                    "code_v1": "ﯞ",
                    "page_number": 85,
                    "line_number": 11,
                    "text": "أَوْ",
                    "translation": {
                        "text": "or",
                        "language_name": "english"
                    }
                },
                {
                    "id": 43532,
                    "position": 27,
                    "char_type_name": "word",
                    "v1_page": 85,
                    "text_uthmani": "جَآءَ",
                    "text_indopak": "جَآءَ",
                    "code_v1": "ﯟ",
                    "page_number": 85,
                    "line_number": 11,
                    "text": "جَآءَ",
                    "translation": {
                        "text": "came",
                        "language_name": "english"
                    }
                },
                {
                    "id": 43533,
                    "position": 28,
                    "char_type_name": "word",
                    "v1_page": 85,
                    "text_uthmani": "أَحَدٌۭ",
                    "text_indopak": "اَحَدٌ",
                    "code_v1": "ﯠ",
                    "page_number": 85,
                    "line_number": 12,
                    "text": "أَحَدٌۭ",
                    "translation": {
                        "text": "one",
                        "language_name": "english"
                    }
                },
                {
                    "id": 43534,
                    "position": 29,
                    "char_type_name": "word",
                    "v1_page": 85,
                    "text_uthmani": "مِّنكُم",
                    "text_indopak": "مِّنۡكُمۡ",
                    "code_v1": "ﯡ",
                    "page_number": 85,
                    "line_number": 12,
                    "text": "مِّنكُم",
                    "translation": {
                        "text": "of you",
                        "language_name": "english"
                    }
                },
                {
                    "id": 43535,
                    "position": 30,
                    "char_type_name": "word",
                    "v1_page": 85,
                    "text_uthmani": "مِّنَ",
                    "text_indopak": "مِّنَ",
                    "code_v1": "ﯢ",
                    "page_number": 85,
                    "line_number": 12,
                    "text": "مِّنَ",
                    "translation": {
                        "text": "from",
                        "language_name": "english"
                    }
                },
                {
                    "id": 43536,
                    "position": 31,
                    "char_type_name": "word",
                    "v1_page": 85,
                    "text_uthmani": "ٱلْغَآئِطِ",
                    "text_indopak": "الۡغَآٮِٕطِ",
                    "code_v1": "ﯣ",
                    "page_number": 85,
                    "line_number": 12,
                    "text": "ٱلْغَآئِطِ",
                    "translation": {
                        "text": "the toilet",
                        "language_name": "english"
                    }
                },
                {
                    "id": 43537,
                    "position": 32,
                    "char_type_name": "word",
                    "v1_page": 85,
                    "text_uthmani": "أَوْ",
                    "text_indopak": "اَوۡ",
                    "code_v1": "ﯤ",
                    "page_number": 85,
                    "line_number": 12,
                    "text": "أَوْ",
                    "translation": {
                        "text": "or",
                        "language_name": "english"
                    }
                },
                {
                    "id": 43538,
                    "position": 33,
                    "char_type_name": "word",
                    "v1_page": 85,
                    "text_uthmani": "لَـٰمَسْتُمُ",
                    "text_indopak": "لٰمَسۡتُمُ",
                    "code_v1": "ﯥ",
                    "page_number": 85,
                    "line_number": 12,
                    "text": "لَـٰمَسْتُمُ",
                    "translation": {
                        "text": "you have touched",
                        "language_name": "english"
                    }
                },
                {
                    "id": 43539,
                    "position": 34,
                    "char_type_name": "word",
                    "v1_page": 85,
                    "text_uthmani": "ٱلنِّسَآءَ",
                    "text_indopak": "النِّسَآءَ",
                    "code_v1": "ﯦ",
                    "page_number": 85,
                    "line_number": 12,
                    "text": "ٱلنِّسَآءَ",
                    "translation": {
                        "text": "the women",
                        "language_name": "english"
                    }
                },
                {
                    "id": 43540,
                    "position": 35,
                    "char_type_name": "word",
                    "v1_page": 85,
                    "text_uthmani": "فَلَمْ",
                    "text_indopak": "فَلَمۡ",
                    "code_v1": "ﯧ",
                    "page_number": 85,
                    "line_number": 12,
                    "text": "فَلَمْ",
                    "translation": {
                        "text": "and not",
                        "language_name": "english"
                    }
                },
                {
                    "id": 43541,
                    "position": 36,
                    "char_type_name": "word",
                    "v1_page": 85,
                    "text_uthmani": "تَجِدُوا۟",
                    "text_indopak": "تَجِدُوۡا",
                    "code_v1": "ﯨ",
                    "page_number": 85,
                    "line_number": 12,
                    "text": "تَجِدُوا۟",
                    "translation": {
                        "text": "you find",
                        "language_name": "english"
                    }
                },
                {
                    "id": 43542,
                    "position": 37,
                    "char_type_name": "word",
                    "v1_page": 85,
                    "text_uthmani": "مَآءًۭ",
                    "text_indopak": "مَآءً",
                    "code_v1": "ﯩ",
                    "page_number": 85,
                    "line_number": 12,
                    "text": "مَآءًۭ",
                    "translation": {
                        "text": "water",
                        "language_name": "english"
                    }
                },
                {
                    "id": 43543,
                    "position": 38,
                    "char_type_name": "word",
                    "v1_page": 85,
                    "text_uthmani": "فَتَيَمَّمُوا۟",
                    "text_indopak": "فَتَيَمَّمُوۡا",
                    "code_v1": "ﯪ",
                    "page_number": 85,
                    "line_number": 13,
                    "text": "فَتَيَمَّمُوا۟",
                    "translation": {
                        "text": "then do tayammum",
                        "language_name": "english"
                    }
                },
                {
                    "id": 43544,
                    "position": 39,
                    "char_type_name": "word",
                    "v1_page": 85,
                    "text_uthmani": "صَعِيدًۭا",
                    "text_indopak": "صَعِيۡدًا",
                    "code_v1": "ﯫ",
                    "page_number": 85,
                    "line_number": 13,
                    "text": "صَعِيدًۭا",
                    "translation": {
                        "text": "(with) earth",
                        "language_name": "english"
                    }
                },
                {
                    "id": 43545,
                    "position": 40,
                    "char_type_name": "word",
                    "v1_page": 85,
                    "text_uthmani": "طَيِّبًۭا",
                    "text_indopak": "طَيِّبًا",
                    "code_v1": "ﯬ",
                    "page_number": 85,
                    "line_number": 13,
                    "text": "طَيِّبًۭا",
                    "translation": {
                        "text": "clean",
                        "language_name": "english"
                    }
                },
                {
                    "id": 43546,
                    "position": 41,
                    "char_type_name": "word",
                    "v1_page": 85,
                    "text_uthmani": "فَٱمْسَحُوا۟",
                    "text_indopak": "فَامۡسَحُوۡا",
                    "code_v1": "ﯭ",
                    "page_number": 85,
                    "line_number": 13,
                    "text": "فَٱمْسَحُوا۟",
                    "translation": {
                        "text": "and wipe (with it)",
                        "language_name": "english"
                    }
                },
                {
                    "id": 43547,
                    "position": 42,
                    "char_type_name": "word",
                    "v1_page": 85,
                    "text_uthmani": "بِوُجُوهِكُمْ",
                    "text_indopak": "بِوُجُوۡهِكُمۡ",
                    "code_v1": "ﯮ",
                    "page_number": 85,
                    "line_number": 13,
                    "text": "بِوُجُوهِكُمْ",
                    "translation": {
                        "text": "your faces",
                        "language_name": "english"
                    }
                },
                {
                    "id": 43548,
                    "position": 43,
                    "char_type_name": "word",
                    "v1_page": 85,
                    "text_uthmani": "وَأَيْدِيكُمْ ۗ",
                    "text_indopak": "وَاَيۡدِيۡكُمۡ​ ؕ",
                    "code_v1": "ﯯﯰ",
                    "page_number": 85,
                    "line_number": 13,
                    "text": "وَأَيْدِيكُمْ ۗ",
                    "translation": {
                        "text": "and your hands",
                        "language_name": "english"
                    }
                },
                {
                    "id": 43550,
                    "position": 44,
                    "char_type_name": "word",
                    "v1_page": 85,
                    "text_uthmani": "إِنَّ",
                    "text_indopak": "اِنَّ",
                    "code_v1": "ﯱ",
                    "page_number": 85,
                    "line_number": 13,
                    "text": "إِنَّ",
                    "translation": {
                        "text": "Indeed",
                        "language_name": "english"
                    }
                },
                {
                    "id": 43551,
                    "position": 45,
                    "char_type_name": "word",
                    "v1_page": 85,
                    "text_uthmani": "ٱللَّهَ",
                    "text_indopak": "اللّٰهَ",
                    "code_v1": "ﯲ",
                    "page_number": 85,
                    "line_number": 14,
                    "text": "ٱللَّهَ",
                    "translation": {
                        "text": "Allah",
                        "language_name": "english"
                    }
                },
                {
                    "id": 43552,
                    "position": 46,
                    "char_type_name": "word",
                    "v1_page": 85,
                    "text_uthmani": "كَانَ",
                    "text_indopak": "كَانَ",
                    "code_v1": "ﯳ",
                    "page_number": 85,
                    "line_number": 14,
                    "text": "كَانَ",
                    "translation": {
                        "text": "is",
                        "language_name": "english"
                    }
                },
                {
                    "id": 43553,
                    "position": 47,
                    "char_type_name": "word",
                    "v1_page": 85,
                    "text_uthmani": "عَفُوًّا",
                    "text_indopak": "عَفُوًّا",
                    "code_v1": "ﯴ",
                    "page_number": 85,
                    "line_number": 14,
                    "text": "عَفُوًّا",
                    "translation": {
                        "text": "Oft-Pardoning",
                        "language_name": "english"
                    }
                },
                {
                    "id": 43554,
                    "position": 48,
                    "char_type_name": "word",
                    "v1_page": 85,
                    "text_uthmani": "غَفُورًا",
                    "text_indopak": "غَفُوۡرًا‏",
                    "code_v1": "ﯵ",
                    "page_number": 85,
                    "line_number": 14,
                    "text": "غَفُورًا",
                    "translation": {
                        "text": "Oft-Forgiving",
                        "language_name": "english"
                    }
                },
                {
                    "id": 43555,
                    "position": 49,
                    "char_type_name": "end",
                    "v1_page": 85,
                    "text_uthmani": "٤٣",
                    "text_indopak": "٤٣",
                    "code_v1": "ﯶ",
                    "page_number": 85,
                    "line_number": 14,
                    "text": "٤٣",
                    "translation": {
                        "text": "(43)",
                        "language_name": "english"
                    }
                }
            ]
        },
        {
            "id": 537,
            "verse_number": 44,
            "verse_key": "4:44",
            "hizb_number": 9,
            "rub_el_hizb_number": 34,
            "ruku_number": 68,
            "manzil_number": 1,
            "sajdah_number": null,
            "text_uthmani_simple": "الم تر الى الذين اوتوا۟ نصيبا من الكتب يشترون الضللة ويريدون ان تضلوا۟ السبيل",
            "text_uthmani": "أَلَمْ تَرَ إِلَى ٱلَّذِينَ أُوتُوا۟ نَصِيبًا مِّنَ ٱلْكِتَـٰبِ يَشْتَرُونَ ٱلضَّلَـٰلَةَ وَيُرِيدُونَ أَن تَضِلُّوا۟ ٱلسَّبِيلَ",
            "page_number": 85,
            "juz_number": 5,
            "words": [
                {
                    "id": 44509,
                    "position": 1,
                    "char_type_name": "word",
                    "v1_page": 85,
                    "text_uthmani": "أَلَمْ",
                    "text_indopak": "اَلَمۡ",
                    "code_v1": "ﯷ",
                    "page_number": 85,
                    "line_number": 14,
                    "text": "أَلَمْ",
                    "translation": {
                        "text": "Did not",
                        "language_name": "english"
                    }
                },
                {
                    "id": 44510,
                    "position": 2,
                    "char_type_name": "word",
                    "v1_page": 85,
                    "text_uthmani": "تَرَ",
                    "text_indopak": "تَرَ",
                    "code_v1": "ﯸ",
                    "page_number": 85,
                    "line_number": 14,
                    "text": "تَرَ",
                    "translation": {
                        "text": "you see",
                        "language_name": "english"
                    }
                },
                {
                    "id": 44511,
                    "position": 3,
                    "char_type_name": "word",
                    "v1_page": 85,
                    "text_uthmani": "إِلَى",
                    "text_indopak": "اِلَى",
                    "code_v1": "ﯹ",
                    "page_number": 85,
                    "line_number": 14,
                    "text": "إِلَى",
                    "translation": {
                        "text": "[towards]",
                        "language_name": "english"
                    }
                },
                {
                    "id": 44512,
                    "position": 4,
                    "char_type_name": "word",
                    "v1_page": 85,
                    "text_uthmani": "ٱلَّذِينَ",
                    "text_indopak": "الَّذِيۡنَ",
                    "code_v1": "ﯺ",
                    "page_number": 85,
                    "line_number": 14,
                    "text": "ٱلَّذِينَ",
                    "translation": {
                        "text": "those who",
                        "language_name": "english"
                    }
                },
                {
                    "id": 44513,
                    "position": 5,
                    "char_type_name": "word",
                    "v1_page": 85,
                    "text_uthmani": "أُوتُوا۟",
                    "text_indopak": "اُوۡتُوۡا",
                    "code_v1": "ﯻ",
                    "page_number": 85,
                    "line_number": 14,
                    "text": "أُوتُوا۟",
                    "translation": {
                        "text": "were given",
                        "language_name": "english"
                    }
                },
                {
                    "id": 44514,
                    "position": 6,
                    "char_type_name": "word",
                    "v1_page": 85,
                    "text_uthmani": "نَصِيبًۭا",
                    "text_indopak": "نَصِيۡبًا",
                    "code_v1": "ﯼ",
                    "page_number": 85,
                    "line_number": 14,
                    "text": "نَصِيبًۭا",
                    "translation": {
                        "text": "a portion",
                        "language_name": "english"
                    }
                },
                {
                    "id": 44515,
                    "position": 7,
                    "char_type_name": "word",
                    "v1_page": 85,
                    "text_uthmani": "مِّنَ",
                    "text_indopak": "مِّنَ",
                    "code_v1": "ﯽ",
                    "page_number": 85,
                    "line_number": 14,
                    "text": "مِّنَ",
                    "translation": {
                        "text": "of",
                        "language_name": "english"
                    }
                },
                {
                    "id": 44516,
                    "position": 8,
                    "char_type_name": "word",
                    "v1_page": 85,
                    "text_uthmani": "ٱلْكِتَـٰبِ",
                    "text_indopak": "الۡكِتٰبِ",
                    "code_v1": "ﯾ",
                    "page_number": 85,
                    "line_number": 15,
                    "text": "ٱلْكِتَـٰبِ",
                    "translation": {
                        "text": "the Book",
                        "language_name": "english"
                    }
                },
                {
                    "id": 44517,
                    "position": 9,
                    "char_type_name": "word",
                    "v1_page": 85,
                    "text_uthmani": "يَشْتَرُونَ",
                    "text_indopak": "يَشۡتَرُوۡنَ",
                    "code_v1": "ﯿ",
                    "page_number": 85,
                    "line_number": 15,
                    "text": "يَشْتَرُونَ",
                    "translation": {
                        "text": "purchasing",
                        "language_name": "english"
                    }
                },
                {
                    "id": 44518,
                    "position": 10,
                    "char_type_name": "word",
                    "v1_page": 85,
                    "text_uthmani": "ٱلضَّلَـٰلَةَ",
                    "text_indopak": "الضَّلٰلَةَ",
                    "code_v1": "ﰀ",
                    "page_number": 85,
                    "line_number": 15,
                    "text": "ٱلضَّلَـٰلَةَ",
                    "translation": {
                        "text": "[the] error",
                        "language_name": "english"
                    }
                },
                {
                    "id": 44519,
                    "position": 11,
                    "char_type_name": "word",
                    "v1_page": 85,
                    "text_uthmani": "وَيُرِيدُونَ",
                    "text_indopak": "وَيُرِيۡدُوۡنَ",
                    "code_v1": "ﰁ",
                    "page_number": 85,
                    "line_number": 15,
                    "text": "وَيُرِيدُونَ",
                    "translation": {
                        "text": "and wishing",
                        "language_name": "english"
                    }
                },
                {
                    "id": 44520,
                    "position": 12,
                    "char_type_name": "word",
                    "v1_page": 85,
                    "text_uthmani": "أَن",
                    "text_indopak": "اَنۡ",
                    "code_v1": "ﰂ",
                    "page_number": 85,
                    "line_number": 15,
                    "text": "أَن",
                    "translation": {
                        "text": "that",
                        "language_name": "english"
                    }
                },
                {
                    "id": 44521,
                    "position": 13,
                    "char_type_name": "word",
                    "v1_page": 85,
                    "text_uthmani": "تَضِلُّوا۟",
                    "text_indopak": "تَضِلُّوا",
                    "code_v1": "ﰃ",
                    "page_number": 85,
                    "line_number": 15,
                    "text": "تَضِلُّوا۟",
                    "translation": {
                        "text": "you stray",
                        "language_name": "english"
                    }
                },
                {
                    "id": 44522,
                    "position": 14,
                    "char_type_name": "word",
                    "v1_page": 85,
                    "text_uthmani": "ٱلسَّبِيلَ",
                    "text_indopak": "السَّبِيۡلَ ؕ‏",
                    "code_v1": "ﰄ",
                    "page_number": 85,
                    "line_number": 15,
                    "text": "ٱلسَّبِيلَ",
                    "translation": {
                        "text": "(from) the way",
                        "language_name": "english"
                    }
                },
                {
                    "id": 44523,
                    "position": 15,
                    "char_type_name": "end",
                    "v1_page": 85,
                    "text_uthmani": "٤٤",
                    "text_indopak": "٤٤",
                    "code_v1": "ﰅ",
                    "page_number": 85,
                    "line_number": 15,
                    "text": "٤٤",
                    "translation": {
                        "text": "(44)",
                        "language_name": "english"
                    }
                }
            ]
        }
    ]
}