{
    "verses": [
        {
            "id": 1640,
            "verse_number": 44,
            "verse_key": "12:44",
            "hizb_number": 24,
            "rub_el_hizb_number": 96,
            "ruku_number": 198,
            "manzil_number": 3,
            "sajdah_number": null,
            "text_uthmani_simple": "قالوا۟ اضغث احلم وما نحن بتاويل الاحلم بعلمين",
            "text_uthmani": "قَالُوٓا۟ أَضْغَـٰثُ أَحْلَـٰمٍ ۖ وَمَا نَحْنُ بِتَأْوِيلِ ٱلْأَحْلَـٰمِ بِعَـٰلِمِينَ",
            "page_number": 241,
            "juz_number": 12,
            "words": [
                {
                    "id": 44672,
                    "position": 1,
                    "char_type_name": "word",
                    "v1_page": 241,
                    "text_uthmani": "قَالُوٓا۟",
                    "text_uthmani_simple": "قالوا۟",
                    "code_v1": "ﭑ",
                    "page_number": 241,
                    "line_number": 1,
                    "text": "قَالُوٓا۟",
                    "translation": {
                        "text": "They said",
                        "language_name": "english"
                    }
                },
                {
                    "id": 44673,
                    "position": 2,
                    "char_type_name": "word",
                    "v1_page": 241,
                    "text_uthmani": "أَضْغَـٰثُ",
                    "text_uthmani_simple": "اضغـث",
                    "code_v1": "ﭒ",
                    "page_number": 241,
                    "line_number": 1,
                    "text": "أَضْغَـٰثُ",
                    "translation": {
                        "text": "Confused",
                        "language_name": "english"
                    }
                },
                {
                    "id": 44674,
                    "position": 3,
                    "char_type_name": "word",
                    "v1_page": 241,
                    "text_uthmani": "أَحْلَـٰمٍۢ ۖ",
                    "text_uthmani_simple": "احلـم",
                    "code_v1": "ﭓﭔ",
                    "page_number": 241,
                    "line_number": 1,
                    "text": "أَحْلَـٰمٍۢ ۖ",
                    "translation": {
                        "text": "dreams",
                        "language_name": "english"
                    }
                },
                {
                    "id": 44676,
                    "position": 4,
                    "char_type_name": "word",
                    "v1_page": 241,
                    "text_uthmani": "وَمَا",
                    "text_uthmani_simple": "وما",
                    "code_v1": "ﭕ",
                    "page_number": 241,
                    "line_number": 1,
                    "text": "وَمَا",
                    "translation": {
                        "text": "and not",
                        "language_name": "english"
                    }
                },
                {
                    "id": 44677,
                    "position": 5,
                    "char_type_name": "word",
                    "v1_page": 241,
                    "text_uthmani": "نَحْنُ",
                    "text_uthmani_simple": "نحن",
                    "code_v1": "ﭖ",
                    "page_number": 241,
                    "line_number": 1,
                    "text": "نَحْنُ",
                    "translation": {
                        "text": "we",
                        "language_name": "english"
                    }
                },
                {
                    "id": 44678,
                    "position": 6,
                    "char_type_name": "word",
                    "v1_page": 241,
                    "text_uthmani": "بِتَأْوِيلِ",
                    "text_uthmani_simple": "بتاويل",
                    "code_v1": "ﭗ",
                    "page_number": 241,
                    "line_number": 1,
                    "text": "بِتَأْوِيلِ",
                    "translation": {
                        "text": "(are) in the interpretation",
                        "language_name": "english"
                    }
                },
                {
                    "id": 44679,
                    "position": 7,
                    "char_type_name": "word",
                    "v1_page": 241,
                    "text_uthmani": "ٱلْأَحْلَـٰمِ",
                    "text_uthmani_simple": "الاحلـم",
                    "code_v1": "ﭘ",
                    "page_number": 241,
                    "line_number": 1,
                    "text": "ٱلْأَحْلَـٰمِ",
                    "translation": {
                        "text": "(of) the dreams",
                        "language_name": "english"
                    }
                },
                {
                    "id": 44680,
                    "position": 8,
                    "char_type_name": "word",
                    "v1_page": 241,
                    "text_uthmani": "بِعَـٰلِمِينَ",
                    "text_uthmani_simple": "بعـلمين",
                    "code_v1": "ﭙ",
                    "page_number": 241,
                    "line_number": 1,
                    "text": "بِعَـٰلِمِينَ",
                    "translation": {
                        "text": "learned",
                        "language_name": "english"
                    }
                },
                {
                    "id": 44681,
                    "position": 9,
                    "char_type_name": "end",
                    "v1_page": 241,
                    "text_uthmani": "٤٤",
                    "text_uthmani_simple": "٤٤",
                    "code_v1": "ﭚ",
                    "page_number": 241,
                    "line_number": 1,
                    "text": "٤٤",
                    "translation": {
                        "text": "(44)",
                        "language_name": "english"
                    }
                }
            ]
        },
        {
            "id": 1641,
            "verse_number": 45,
            "verse_key": "12:45",
            "hizb_number": 24,
            "rub_el_hizb_number": 96,
            "ruku_number": 198,
            "manzil_number": 3,
            "sajdah_number": null,
            "text_uthmani_simple": "وقال الذى نجا منهما وادكر بعد امة انا۠ انبئكم بتاويله فارسلون",
            "text_uthmani": "وَقَالَ ٱلَّذِى نَجَا مِنْهُمَا وَٱدَّكَرَ بَعْدَ أُمَّةٍ أَنَا۠ أُنَبِّئُكُم بِتَأْوِيلِهِۦ فَأَرْسِلُونِ",
            "page_number": 241,
            "juz_number": 12,
            "words": [
                {
                    "id": 45354,
                    "position": 1,
                    "char_type_name": "word",
                    "v1_page": 241,
                    "text_uthmani": "وَقَالَ",
                    "text_uthmani_simple": "وقال",
                    "code_v1": "ﭛ",
                    "page_number": 241,
                    "line_number": 2,
                    "text": "وَقَالَ",
                    "translation": {
                        "text": "But said",
                        "language_name": "english"
                    }
                },
                {
                    "id": 45355,
                    "position": 2,
                    "char_type_name": "word",
                    "v1_page": 241,
                    "text_uthmani": "ٱلَّذِى",
                    "text_uthmani_simple": "الذى",
                    "code_v1": "ﭜ",
                    "page_number": 241,
                    "line_number": 2,
                    "text": "ٱلَّذِى",
                    "translation": {
                        "text": "the one who",
                        "language_name": "english"
                    }
                },
                {
                    "id": 45356,
                    "position": 3,
                    "char_type_name": "word",
                    "v1_page": 241,
                    "text_uthmani": "نَجَا",
                    "text_uthmani_simple": "نجا",
                    "code_v1": "ﭝ",
                    "page_number": 241,
                    "line_number": 2,
                    "text": "نَجَا",
                    "translation": {
                        "text": "was saved",
                        "language_name": "english"
                    }
                },
                {
                    "id": 45357,
                    "position": 4,
                    "char_type_name": "word",
                    "v1_page": 241,
                    "text_uthmani": "مِنْهُمَا",
                    "text_uthmani_simple": "منهما",
                    "code_v1": "ﭞ",
                    "page_number": 241,
                    "line_number": 2,
                    "text": "مِنْهُمَا",
                    "translation": {
                        "text": "of the two",
                        "language_name": "english"
                    }
                },
                {
                    "id": 45358,
                    "position": 5,
                    "char_type_name": "word",
                    "v1_page": 241,
                    "text_uthmani": "وَٱدَّكَرَ",
                    "text_uthmani_simple": "وادكر",
                    "code_v1": "ﭟ",
                    "page_number": 241,
                    "line_number": 2,
                    "text": "وَٱدَّكَرَ",
                    "translation": {
                        "text": "and remembered",
                        "language_name": "english"
                    }
                },
                {
                    "id": 45359,
                    "position": 6,
                    "char_type_name": "word",
                    "v1_page": 241,
                    "text_uthmani": "بَعْدَ",
                    "text_uthmani_simple": "بعد",
                    "code_v1": "ﭠ",
                    "page_number": 241,
                    "line_number": 2,
                    "text": "بَعْدَ",
                    "translation": {
                        "text": "after",
                        "language_name": "english"
                    }
                },
                {
                    "id": 45360,
                    "position": 7,
                    "char_type_name": "word",
                    "v1_page": 241,
                    "text_uthmani": "أُمَّةٍ",
                    "text_uthmani_simple": "امة",
                    "code_v1": "ﭡ",
                    "page_number": 241,
                    "line_number": 2,
                    "text": "أُمَّةٍ",
                    "translation": {
                        "text": "a period",
                        "language_name": "english"
                    }
                },
                {
                    "id": 45361,
                    "position": 8,
                    "char_type_name": "word",
                    "v1_page": 241,
                    "text_uthmani": "أَنَا۠",
                    "text_uthmani_simple": "انا۠",
                    "code_v1": "ﭢ",
                    "page_number": 241,
                    "line_number": 2,
                    "text": "أَنَا۠",
                    "translation": {
                        "text": "I",
                        "language_name": "english"
                    }
                },
                {
                    "id": 45362,
                    "position": 9,
                    "char_type_name": "word",
                    "v1_page": 241,
                    "text_uthmani": "أُنَبِّئُكُم",
                    "text_uthmani_simple": "انبئكم",
                    "code_v1": "ﭣ",
                    "page_number": 241,
                    "line_number": 2,
                    "text": "أُنَبِّئُكُم",
                    "translation": {
                        "text": "[I] will inform you",
                        "language_name": "english"
                    }
                },
                {
                    "id": 45363,
                    "position": 10,
                    "char_type_name": "word",
                    "v1_page": 241,
                    "text_uthmani": "بِتَأْوِيلِهِۦ",
                    "text_uthmani_simple": "بتاويله",
                    "code_v1": "ﭤ",
                    "page_number": 241,
                    "line_number": 2,
                    "text": "بِتَأْوِيلِهِۦ",
                    "translation": {
                        "text": "of its interpretation",
                        "language_name": "english"
                    }
                },
                {
                    "id": 45364,
                    "position": 11,
                    "char_type_name": "word",
                    "v1_page": 241,
                    "text_uthmani": "فَأَرْسِلُونِ",
                    "text_uthmani_simple": "فارسلون",
                    "code_v1": "ﭥ",
                    "page_number": 241,
                    "line_number": 3,
                    "text": "فَأَرْسِلُونِ",
                    "translation": {
                        "text": "so send me forth",
                        "language_name": "english"
                    }
                },
                {
                    "id": 45365,
                    "position": 12,
                    "char_type_name": "end",
                    "v1_page": 241,
                    "text_uthmani": "٤٥",
                    "text_uthmani_simple": "٤٥",
                    "code_v1": "ﭦ",
                    "page_number": 241,
                    "line_number": 3,
                    "text": "٤٥",
                    "translation": {
                        "text": "(45)",
                        "language_name": "english"
                    }
                }
            ]
        },
        {
            "id": 1642,
            "verse_number": 46,
            "verse_key": "12:46",
            "hizb_number": 24,
            "rub_el_hizb_number": 96,
            "ruku_number": 198,
            "manzil_number": 3,
            "sajdah_number": null,
            "text_uthmani_simple": "يوسف ايها الصديق افتنا فى سبع بقرت سمان ياكلهن سبع عجاف وسبع سنۢبلت خضر واخر يابست لعلى ارجع الى الناس لعلهم يعلمون",
            "text_uthmani": "يُوسُفُ أَيُّهَا ٱلصِّدِّيقُ أَفْتِنَا فِى سَبْعِ بَقَرَٰتٍ سِمَانٍ يَأْكُلُهُنَّ سَبْعٌ عِجَافٌ وَسَبْعِ سُنۢبُلَـٰتٍ خُضْرٍ وَأُخَرَ يَابِسَـٰتٍ لَّعَلِّىٓ أَرْجِعُ إِلَى ٱلنَّاسِ لَعَلَّهُمْ يَعْلَمُونَ",
            "page_number": 241,
            "juz_number": 12,
            "words": [
                {
                    "id": 46095,
                    "position": 1,
                    "char_type_name": "word",
                    "v1_page": 241,
                    "text_uthmani": "يُوسُفُ",
                    "text_uthmani_simple": "يوسف",
                    "code_v1": "ﭧ",
                    "page_number": 241,
                    "line_number": 3,
                    "text": "يُوسُفُ",
                    "translation": {
                        "text": "Yusuf",
                        "language_name": "english"
                    }
                },
                {
                    "id": 46096,
                    "position": 2,
                    "char_type_name": "word",
                    "v1_page": 241,
                    "text_uthmani": "أَيُّهَا",
                    "text_uthmani_simple": "ايها",
                    "code_v1": "ﭨ",
                    "page_number": 241,
                    "line_number": 3,
                    "text": "أَيُّهَا",
                    "translation": {
                        "text": "O",
                        "language_name": "english"
                    }
                },
                {
                    "id": 46097,
                    "position": 3,
                    "char_type_name": "word",
                    "v1_page": 241,
                    "text_uthmani": "ٱلصِّدِّيقُ",
                    "text_uthmani_simple": "الصديق",
                    "code_v1": "ﭩ",
                    "page_number": 241,
                    "line_number": 3,
                    "text": "ٱلصِّدِّيقُ",
                    "translation": {
                        "text": "the truthful one",
                        "language_name": "english"
                    }
                },
                {
                    "id": 46098,
                    "position": 4,
                    "char_type_name": "word",
                    "v1_page": 241,
                    "text_uthmani": "أَفْتِنَا",
                    "text_uthmani_simple": "افتنا",
                    "code_v1": "ﭪ",
                    "page_number": 241,
                    "line_number": 3,
                    "text": "أَفْتِنَا",
                    "translation": {
                        "text": "Explain to us",
                        "language_name": "english"
                    }
                },
                {
                    "id": 46099,
                    "position": 5,
                    "char_type_name": "word",
                    "v1_page": 241,
                    "text_uthmani": "فِى",
                    "text_uthmani_simple": "فى",
                    "code_v1": "ﭫ",
                    "page_number": 241,
                    "line_number": 3,
                    "text": "فِى",
                    "translation": {
                        "text": "about",
                        "language_name": "english"
                    }
                },
                {
                    "id": 46100,
                    "position": 6,
                    "char_type_name": "word",
                    "v1_page": 241,
                    "text_uthmani": "سَبْعِ",
                    "text_uthmani_simple": "سبع",
                    "code_v1": "ﭬ",
                    "page_number": 241,
                    "line_number": 3,
                    "text": "سَبْعِ",
                    "translation": {
                        "text": "(the) seven",
                        "language_name": "english"
                    }
                },
                {
                    "id": 46101,
                    "position": 7,
                    "char_type_name": "word",
                    "v1_page": 241,
                    "text_uthmani": "بَقَرَٰتٍۢ",
                    "text_uthmani_simple": "بقرت",
                    "code_v1": "ﭭ",
                    "page_number": 241,
                    "line_number": 3,
                    "text": "بَقَرَٰتٍۢ",
                    "translation": {
                        "text": "cows",
                        "language_name": "english"
                    }
                },
                {
                    "id": 46102,
                    "position": 8,
                    "char_type_name": "word",
                    "v1_page": 241,
                    "text_uthmani": "سِمَانٍۢ",
                    "text_uthmani_simple": "سمان",
                    "code_v1": "ﭮ",
                    "page_number": 241,
                    "line_number": 4,
                    "text": "سِمَانٍۢ",
                    "translation": {
                        "text": "fat",
                        "language_name": "english"
                    }
                },
                {
                    "id": 46103,
                    "position": 9,
                    "char_type_name": "word",
                    "v1_page": 241,
                    "text_uthmani": "يَأْكُلُهُنَّ",
                    "text_uthmani_simple": "ياكلهن",
                    "code_v1": "ﭯ",
                    "page_number": 241,
                    "line_number": 4,
                    "text": "يَأْكُلُهُنَّ",
                    "translation": {
                        "text": "eating them",
                        "language_name": "english"
                    }
                },
                {
                    "id": 46104,
                    "position": 10,
                    "char_type_name": "word",
                    "v1_page": 241,
                    "text_uthmani": "سَبْعٌ",
                    "text_uthmani_simple": "سبع",
                    "code_v1": "ﭰ",
                    "page_number": 241,
                    "line_number": 4,
                    "text": "سَبْعٌ",
                    "translation": {
                        "text": "seven",
                        "language_name": "english"
                    }
                },
                {
                    "id": 46105,
                    "position": 11,
                    "char_type_name": "word",
                    "v1_page": 241,
                    "text_uthmani": "عِجَافٌۭ",
                    "text_uthmani_simple": "عجافۭ",
                    "code_v1": "ﭱ",
                    "page_number": 241,
                    "line_number": 4,
                    "text": "عِجَافٌۭ",
                    "translation": {
                        "text": "lean ones",
                        "language_name": "english"
                    }
                },
                {
                    "id": 46106,
                    "position": 12,
                    "char_type_name": "word",
                    "v1_page": 241,
                    "text_uthmani": "وَسَبْعِ",
                    "text_uthmani_simple": "وسبع",
                    "code_v1": "ﭲ",
                    "page_number": 241,
                    "line_number": 4,
                    "text": "وَسَبْعِ",
                    "translation": {
                        "text": "and seven",
                        "language_name": "english"
                    }
                },
                {
                    "id": 46107,
                    "position": 13,
                    "char_type_name": "word",
                    "v1_page": 241,
                    "text_uthmani": "سُنۢبُلَـٰتٍ",
                    "text_uthmani_simple": "سنبلـت",
                    "code_v1": "ﭳ",
                    "page_number": 241,
                    "line_number": 4,
                    "text": "سُنۢبُلَـٰتٍ",
                    "translation": {
                        "text": "ears (of corn)",
                        "language_name": "english"
                    }
                },
                {
                    "id": 46108,
                    "position": 14,
                    "char_type_name": "word",
                    "v1_page": 241,
                    "text_uthmani": "خُضْرٍۢ",
                    "text_uthmani_simple": "خضر",
                    "code_v1": "ﭴ",
                    "page_number": 241,
                    "line_number": 4,
                    "text": "خُضْرٍۢ",
                    "translation": {
                        "text": "green",
                        "language_name": "english"
                    }
                },
                {
                    "id": 46109,
                    "position": 15,
                    "char_type_name": "word",
                    "v1_page": 241,
                    "text_uthmani": "وَأُخَرَ",
                    "text_uthmani_simple": "واخر",
                    "code_v1": "ﭵ",
                    "page_number": 241,
                    "line_number": 5,
                    "text": "وَأُخَرَ",
                    "translation": {
                        "text": "and other",
                        "language_name": "english"
                    }
                },
                {
                    "id": 46110,
                    "position": 16,
                    "char_type_name": "word",
                    "v1_page": 241,
                    "text_uthmani": "يَابِسَـٰتٍۢ",
                    "text_uthmani_simple": "يابسـت",
                    "code_v1": "ﭶ",
                    "page_number": 241,
                    "line_number": 5,
                    "text": "يَابِسَـٰتٍۢ",
                    "translation": {
                        "text": "dry",
                        "language_name": "english"
                    }
                },
                {
                    "id": 46111,
                    "position": 17,
                    "char_type_name": "word",
                    "v1_page": 241,
                    "text_uthmani": "لَّعَلِّىٓ",
                    "text_uthmani_simple": "لعلى",
                    "code_v1": "ﭷ",
                    "page_number": 241,
                    "line_number": 5,
                    "text": "لَّعَلِّىٓ",
                    "translation": {
                        "text": "that I may",
                        "language_name": "english"
                    }
                },
                {
                    "id": 46112,
                    "position": 18,
                    "char_type_name": "word",
                    "v1_page": 241,
                    "text_uthmani": "أَرْجِعُ",
                    "text_uthmani_simple": "ارجع",
                    "code_v1": "ﭸ",
                    "page_number": 241,
                    "line_number": 5,
                    "text": "أَرْجِعُ",
                    "translation": {
                        "text": "return",
                        "language_name": "english"
                    }
                },
                {
                    "id": 46113,
                    "position": 19,
                    "char_type_name": "word",
                    "v1_page": 241,
                    "text_uthmani": "إِلَى",
                    "text_uthmani_simple": "الى",
                    "code_v1": "ﭹ",
                    "page_number": 241,
                    "line_number": 5,
                    "text": "إِلَى",
                    "translation": {
                        "text": "to",
                        "language_name": "english"
                    }
                },
                {
                    "id": 46114,
                    "position": 20,
                    "char_type_name": "word",
                    "v1_page": 241,
                    "text_uthmani": "ٱلنَّاسِ",
                    "text_uthmani_simple": "الناس",
                    "code_v1": "ﭺ",
                    "page_number": 241,
                    "line_number": 5,
                    "text": "ٱلنَّاسِ",
                    "translation": {
                        "text": "the people",
                        "language_name": "english"
                    }
                },
                {
                    "id": 46115,
                    "position": 21,
                    "char_type_name": "word",
                    "v1_page": 241,
                    "text_uthmani": "لَعَلَّهُمْ",
                    "text_uthmani_simple": "لعلهم",
                    "code_v1": "ﭻ",
                    "page_number": 241,
                    "line_number": 5,
                    "text": "لَعَلَّهُمْ",
                    "translation": {
                        "text": "so that they may",
                        "language_name": "english"
                    }
                },
                {
                    "id": 46116,
                    "position": 22,
                    "char_type_name": "word",
                    "v1_page": 241,
                    "text_uthmani": "يَعْلَمُونَ",
                    "text_uthmani_simple": "يعلمون",
                    "code_v1": "ﭼ",
                    "page_number": 241,
                    "line_number": 5,
                    "text": "يَعْلَمُونَ",
                    "translation": {
                        "text": "know",
                        "language_name": "english"
                    }
                },
                {
                    "id": 46117,
                    "position": 23,
                    "char_type_name": "end",
                    "v1_page": 241,
                    "text_uthmani": "٤٦",
                    "text_uthmani_simple": "٤٦",
                    "code_v1": "ﭽ",
                    "page_number": 241,
                    "line_number": 5,
                    "text": "٤٦",
                    "translation": {
                        "text": "(46)",
                        "language_name": "english"
                    }
                }
            ]
        },
        {
            "id": 1643,
            "verse_number": 47,
            "verse_key": "12:47",
            "hizb_number": 24,
            "rub_el_hizb_number": 96,
            "ruku_number": 198,
            "manzil_number": 3,
            "sajdah_number": null,
            "text_uthmani_simple": "قال تزرعون سبع سنين دابا فما حصدتم فذروه فى سنۢبله الا قليلا مما تاكلون",
            "text_uthmani": "قَالَ تَزْرَعُونَ سَبْعَ سِنِينَ دَأَبًا فَمَا حَصَدتُّمْ فَذَرُوهُ فِى سُنۢبُلِهِۦٓ إِلَّا قَلِيلًا مِّمَّا تَأْكُلُونَ",
            "page_number": 241,
            "juz_number": 12,
            "words": [
                {
                    "id": 46705,
                    "position": 1,
                    "char_type_name": "word",
                    "v1_page": 241,
                    "text_uthmani": "قَالَ",
                    "text_uthmani_simple": "قال",
                    "code_v1": "ﭾ",
                    "page_number": 241,
                    "line_number": 5,
                    "text": "قَالَ",
                    "translation": {
                        "text": "He said",
                        "language_name": "english"
                    }
                },
                {
                    "id": 46706,
                    "position": 2,
                    "char_type_name": "word",
                    "v1_page": 241,
                    "text_uthmani": "تَزْرَعُونَ",
                    "text_uthmani_simple": "تزرعون",
                    "code_v1": "ﭿ",
                    "page_number": 241,
                    "line_number": 6,
                    "text": "تَزْرَعُونَ",
                    "translation": {
                        "text": "You will sow",
                        "language_name": "english"
                    }
                },
                {
                    "id": 46707,
                    "position": 3,
                    "char_type_name": "word",
                    "v1_page": 241,
                    "text_uthmani": "سَبْعَ",
                    "text_uthmani_simple": "سبع",
                    "code_v1": "ﮀ",
                    "page_number": 241,
                    "line_number": 6,
                    "text": "سَبْعَ",
                    "translation": {
                        "text": "(for) seven",
                        "language_name": "english"
                    }
                },
                {
                    "id": 46708,
                    "position": 4,
                    "char_type_name": "word",
                    "v1_page": 241,
                    "text_uthmani": "سِنِينَ",
                    "text_uthmani_simple": "سنين",
                    "code_v1": "ﮁ",
                    "page_number": 241,
                    "line_number": 6,
                    "text": "سِنِينَ",
                    "translation": {
                        "text": "years",
                        "language_name": "english"
                    }
                },
                {
                    "id": 46709,
                    "position": 5,
                    "char_type_name": "word",
                    "v1_page": 241,
                    "text_uthmani": "دَأَبًۭا",
                    "text_uthmani_simple": "دابۭا",
                    "code_v1": "ﮂ",
                    "page_number": 241,
                    "line_number": 6,
                    "text": "دَأَبًۭا",
                    "translation": {
                        "text": "as usual",
                        "language_name": "english"
                    }
                },
                {
                    "id": 46710,
                    "position": 6,
                    "char_type_name": "word",
                    "v1_page": 241,
                    "text_uthmani": "فَمَا",
                    "text_uthmani_simple": "فما",
                    "code_v1": "ﮃ",
                    "page_number": 241,
                    "line_number": 6,
                    "text": "فَمَا",
                    "translation": {
                        "text": "and that which",
                        "language_name": "english"
                    }
                },
                {
                    "id": 46711,
                    "position": 7,
                    "char_type_name": "word",
                    "v1_page": 241,
                    "text_uthmani": "حَصَدتُّمْ",
                    "text_uthmani_simple": "حصدتم",
                    "code_v1": "ﮄ",
                    "page_number": 241,
                    "line_number": 6,
                    "text": "حَصَدتُّمْ",
                    "translation": {
                        "text": "you reap",
                        "language_name": "english"
                    }
                },
                {
                    "id": 46712,
                    "position": 8,
                    "char_type_name": "word",
                    "v1_page": 241,
                    "text_uthmani": "فَذَرُوهُ",
                    "text_uthmani_simple": "فذروه",
                    "code_v1": "ﮅ",
                    "page_number": 241,
                    "line_number": 6,
                    "text": "فَذَرُوهُ",
                    "translation": {
                        "text": "so leave it",
                        "language_name": "english"
                    }
                },
                {
                    "id": 46713,
                    "position": 9,
                    "char_type_name": "word",
                    "v1_page": 241,
                    "text_uthmani": "فِى",
                    "text_uthmani_simple": "فى",
                    "code_v1": "ﮆ",
                    "page_number": 241,
                    "line_number": 6,
                    "text": "فِى",
                    "translation": {
                        "text": "in",
                        "language_name": "english"
                    }
                },
                {
                    "id": 46714,
                    "position": 10,
                    "char_type_name": "word",
                    "v1_page": 241,
                    "text_uthmani": "سُنۢبُلِهِۦٓ",
                    "text_uthmani_simple": "سنبله",
                    "code_v1": "ﮇ",
                    "page_number": 241,
                    "line_number": 6,
                    "text": "سُنۢبُلِهِۦٓ",
                    "translation": {
                        "text": "its ears",
                        "language_name": "english"
                    }
                },
                {
                    "id": 46715,
                    "position": 11,
                    "char_type_name": "word",
                    "v1_page": 241,
                    "text_uthmani": "إِلَّا",
                    "text_uthmani_simple": "الا",
                    "code_v1": "ﮈ",
                    "page_number": 241,
                    "line_number": 6,
                    "text": "إِلَّا",
                    "translation": {
                        "text": "except",
                        "language_name": "english"
                    }
                },
                {
                    "id": 46716,
                    "position": 12,
                    "char_type_name": "word",
                    "v1_page": 241,
                    "text_uthmani": "قَلِيلًۭا",
                    "text_uthmani_simple": "قليلۭا",
                    "code_v1": "ﮉ",
                    "page_number": 241,
                    "line_number": 7,
                    "text": "قَلِيلًۭا",
                    "translation": {
                        "text": "a little",
                        "language_name": "english"
                    }
                },
                {
                    "id": 46717,
                    "position": 13,
                    "char_type_name": "word",
                    "v1_page": 241,
                    "text_uthmani": "مِّمَّا",
                    "text_uthmani_simple": "مما",
                    "code_v1": "ﮊ",
                    "page_number": 241,
                    "line_number": 7,
                    "text": "مِّمَّا",
                    "translation": {
                        "text": "from which",
                        "language_name": "english"
                    }
                },
                {
                    "id": 46718,
                    "position": 14,
                    "char_type_name": "word",
                    "v1_page": 241,
                    "text_uthmani": "تَأْكُلُونَ",
                    "text_uthmani_simple": "تاكلون",
                    "code_v1": "ﮋ",
                    "page_number": 241,
                    "line_number": 7,
                    "text": "تَأْكُلُونَ",
                    "translation": {
                        "text": "you (will) eat",
                        "language_name": "english"
                    }
                },
                {
                    "id": 46719,
                    "position": 15,
                    "char_type_name": "end",
                    "v1_page": 241,
                    "text_uthmani": "٤٧",
                    "text_uthmani_simple": "٤٧",
                    "code_v1": "ﮌ",
                    "page_number": 241,
                    "line_number": 7,
                    "text": "٤٧",
                    "translation": {
                        "text": "(47)",
                        "language_name": "english"
                    }
                }
            ]
        },
        {
            "id": 1644,
            "verse_number": 48,
            "verse_key": "12:48",
            "hizb_number": 24,
            "rub_el_hizb_number": 96,
            "ruku_number": 198,
            "manzil_number": 3,
            "sajdah_number": null,
            "text_uthmani_simple": "ثم ياتى منۢ بعد ذلك سبع شداد ياكلن ما قدمتم لهن الا قليلا مما تحصنون",
            "text_uthmani": "ثُمَّ يَأْتِى مِنۢ بَعْدِ ذَٰلِكَ سَبْعٌ شِدَادٌ يَأْكُلْنَ مَا قَدَّمْتُمْ لَهُنَّ إِلَّا قَلِيلًا مِّمَّا تُحْصِنُونَ",
            "page_number": 241,
            "juz_number": 12,
            "words": [
                {
                    "id": 47232,
                    "position": 1,
                    "char_type_name": "word",
                    "v1_page": 241,
                    "text_uthmani": "ثُمَّ",
                    "text_uthmani_simple": "ثم",
                    "code_v1": "ﮍ",
                    "page_number": 241,
                    "line_number": 7,
                    "text": "ثُمَّ",
                    "translation": {
                        "text": "Then",
                        "language_name": "english"
                    }
                },
                {
                    "id": 47233,
                    "position": 2,
                    "char_type_name": "word",
                    "v1_page": 241,
                    "text_uthmani": "يَأْتِى",
                    "text_uthmani_simple": "ياتى",
                    "code_v1": "ﮎ",
                    "page_number": 241,
                    "line_number": 7,
                    "text": "يَأْتِى",
                    "translation": {
                        "text": "will come",
                        "language_name": "english"
                    }
                },
                {
                    "id": 47234,
                    "position": 3,
                    "char_type_name": "word",
                    "v1_page": 241,
                    "text_uthmani": "مِنۢ",
                    "text_uthmani_simple": "من",
                    "code_v1": "ﮏ",
                    "page_number": 241,
                    "line_number": 7,
                    "text": "مِنۢ",
                    "translation": {
                        "text": "after",
                        "language_name": "english"
                    }
                },
                {
                    "id": 47235,
                    "position": 4,
                    "char_type_name": "word",
                    "v1_page": 241,
                    "text_uthmani": "بَعْدِ",
                    "text_uthmani_simple": "بعد",
                    "code_v1": "ﮐ",
                    "page_number": 241,
                    "line_number": 7,
                    "text": "بَعْدِ",
                    "translation": {
                        "text": "after",
                        "language_name": "english"
                    }
                },
                {
                    "id": 47236,
                    "position": 5,
                    "char_type_name": "word",
                    "v1_page": 241,
                    "text_uthmani": "ذَٰلِكَ",
                    "text_uthmani_simple": "ذلك",
                    "code_v1": "ﮑ",
                    "page_number": 241,
                    "line_number": 7,
                    "text": "ذَٰلِكَ",
                    "translation": {
                        "text": "that",
                        "language_name": "english"
                    }
                },
                {
                    "id": 47237,
                    "position": 6,
                    "char_type_name": "word",
                    "v1_page": 241,
                    "text_uthmani": "سَبْعٌۭ",
                    "text_uthmani_simple": "سبعۭ",
                    "code_v1": "ﮒ",
                    "page_number": 241,
                    "line_number": 7,
                    "text": "سَبْعٌۭ",
                    "translation": {
                        "text": "seven",
                        "language_name": "english"
                    }
                },
                {
                    "id": 47238,
                    "position": 7,
                    "char_type_name": "word",
                    "v1_page": 241,
                    "text_uthmani": "شِدَادٌۭ",
                    "text_uthmani_simple": "شدادۭ",
                    "code_v1": "ﮓ",
                    "page_number": 241,
                    "line_number": 7,
                    "text": "شِدَادٌۭ",
                    "translation": {
                        "text": "hard (years)",
                        "language_name": "english"
                    }
                },
                {
                    "id": 47239,
                    "position": 8,
                    "char_type_name": "word",
                    "v1_page": 241,
                    "text_uthmani": "يَأْكُلْنَ",
                    "text_uthmani_simple": "ياكلن",
                    "code_v1": "ﮔ",
                    "page_number": 241,
                    "line_number": 7,
                    "text": "يَأْكُلْنَ",
                    "translation": {
                        "text": "(which will) consume",
                        "language_name": "english"
                    }
                },
                {
                    "id": 47240,
                    "position": 9,
                    "char_type_name": "word",
                    "v1_page": 241,
                    "text_uthmani": "مَا",
                    "text_uthmani_simple": "ما",
                    "code_v1": "ﮕ",
                    "page_number": 241,
                    "line_number": 8,
                    "text": "مَا",
                    "translation": {
                        "text": "what",
                        "language_name": "english"
                    }
                },
                {
                    "id": 47241,
                    "position": 10,
                    "char_type_name": "word",
                    "v1_page": 241,
                    "text_uthmani": "قَدَّمْتُمْ",
                    "text_uthmani_simple": "قدمتم",
                    "code_v1": "ﮖ",
                    "page_number": 241,
                    "line_number": 8,
                    "text": "قَدَّمْتُمْ",
                    "translation": {
                        "text": "you advanced",
                        "language_name": "english"
                    }
                },
                {
                    "id": 47242,
                    "position": 11,
                    "char_type_name": "word",
                    "v1_page": 241,
                    "text_uthmani": "لَهُنَّ",
                    "text_uthmani_simple": "لهن",
                    "code_v1": "ﮗ",
                    "page_number": 241,
                    "line_number": 8,
                    "text": "لَهُنَّ",
                    "translation": {
                        "text": "for them",
                        "language_name": "english"
                    }
                },
                {
                    "id": 47243,
                    "position": 12,
                    "char_type_name": "word",
                    "v1_page": 241,
                    "text_uthmani": "إِلَّا",
                    "text_uthmani_simple": "الا",
                    "code_v1": "ﮘ",
                    "page_number": 241,
                    "line_number": 8,
                    "text": "إِلَّا",
                    "translation": {
                        "text": "except",
                        "language_name": "english"
                    }
                },
                {
                    "id": 47244,
                    "position": 13,
                    "char_type_name": "word",
                    "v1_page": 241,
                    "text_uthmani": "قَلِيلًۭا",
                    "text_uthmani_simple": "قليلۭا",
                    "code_v1": "ﮙ",
                    "page_number": 241,
                    "line_number": 8,
                    "text": "قَلِيلًۭا",
                    "translation": {
                        "text": "a little",
                        "language_name": "english"
                    }
                },
                {
                    "id": 47245,
                    "position": 14,
                    "char_type_name": "word",
                    "v1_page": 241,
                    "text_uthmani": "مِّمَّا",
                    "text_uthmani_simple": "مما",
                    "code_v1": "ﮚ",
                    "page_number": 241,
                    "line_number": 8,
                    "text": "مِّمَّا",
                    "translation": {
                        "text": "of what",
                        "language_name": "english"
                    }
                },
                {
                    "id": 47246,
                    "position": 15,
                    "char_type_name": "word",
                    "v1_page": 241,
                    "text_uthmani": "تُحْصِنُونَ",
                    "text_uthmani_simple": "تحصنون",
                    "code_v1": "ﮛ",
                    "page_number": 241,
                    "line_number": 8,
                    "text": "تُحْصِنُونَ",
                    "translation": {
                        "text": "you (will) store",
                        "language_name": "english"
                    }
                },
                {
                    "id": 47247,
                    "position": 16,
                    "char_type_name": "end",
                    "v1_page": 241,
                    "text_uthmani": "٤٨",
                    "text_uthmani_simple": "٤٨",
                    "code_v1": "ﮜ",
                    "page_number": 241,
                    "line_number": 8,
                    "text": "٤٨",
                    "translation": {
                        "text": "(48)",
                        "language_name": "english"
                    }
                }
            ]
        },
        {
            "id": 1645,
            "verse_number": 49,
            "verse_key": "12:49",
            "hizb_number": 24,
            "rub_el_hizb_number": 96,
            "ruku_number": 198,
            "manzil_number": 3,
            "sajdah_number": null,
            "text_uthmani_simple": "ثم ياتى منۢ بعد ذلك عام فيه يغاث الناس وفيه يعصرون",
            "text_uthmani": "ثُمَّ يَأْتِى مِنۢ بَعْدِ ذَٰلِكَ عَامٌ فِيهِ يُغَاثُ ٱلنَّاسُ وَفِيهِ يَعْصِرُونَ",
            "page_number": 241,
            "juz_number": 12,
            "words": [
                {
                    "id": 48199,
                    "position": 1,
                    "char_type_name": "word",
                    "v1_page": 241,
                    "text_uthmani": "ثُمَّ",
                    "text_uthmani_simple": "ثم",
                    "code_v1": "ﮝ",
                    "page_number": 241,
                    "line_number": 8,
                    "text": "ثُمَّ",
                    "translation": {
                        "text": "Then",
                        "language_name": "english"
                    }
                },
                {
                    "id": 48200,
                    "position": 2,
                    "char_type_name": "word",
                    "v1_page": 241,
                    "text_uthmani": "يَأْتِى",
                    "text_uthmani_simple": "ياتى",
                    "code_v1": "ﮞ",
                    "page_number": 241,
                    "line_number": 8,
                    "text": "يَأْتِى",
                    "translation": {
                        "text": "will come",
                        "language_name": "english"
                    }
                },
                {
                    "id": 48201,
                    "position": 3,
                    "char_type_name": "word",
                    "v1_page": 241,
                    "text_uthmani": "مِنۢ",
                    "text_uthmani_simple": "من",
                    "code_v1": "ﮟ",
                    "page_number": 241,
                    "line_number": 8,
                    "text": "مِنۢ",
                    "translation": {
                        "text": "after",
                        "language_name": "english"
                    }
                },
                {
                    "id": 48202,
                    "position": 4,
                    "char_type_name": "word",
                    "v1_page": 241,
                    "text_uthmani": "بَعْدِ",
                    "text_uthmani_simple": "بعد",
                    "code_v1": "ﮠ",
                    "page_number": 241,
                    "line_number": 8,
                    "text": "بَعْدِ",
                    "translation": {
                        "text": "after",
                        "language_name": "english"
                    }
                },
                {
                    "id": 48203,
                    "position": 5,
                    "char_type_name": "word",
                    "v1_page": 241,
                    "text_uthmani": "ذَٰلِكَ",
                    "text_uthmani_simple": "ذلك",
                    "code_v1": "ﮡ",
                    "page_number": 241,
                    "line_number": 8,
                    "text": "ذَٰلِكَ",
                    "translation": {
                        "text": "that",
                        "language_name": "english"
                    }
                },
                {
                    "id": 48204,
                    "position": 6,
                    "char_type_name": "word",
                    "v1_page": 241,
                    "text_uthmani": "عَامٌۭ",
                    "text_uthmani_simple": "عامۭ",
                    "code_v1": "ﮢ",
                    "page_number": 241,
                    "line_number": 9,
                    "text": "عَامٌۭ",
                    "translation": {
                        "text": "a year",
                        "language_name": "english"
                    }
                },
                {
                    "id": 48205,
                    "position": 7,
                    "char_type_name": "word",
                    "v1_page": 241,
                    "text_uthmani": "فِيهِ",
                    "text_uthmani_simple": "فيه",
                    "code_v1": "ﮣ",
                    "page_number": 241,
                    "line_number": 9,
                    "text": "فِيهِ",
                    "translation": {
                        "text": "in it",
                        "language_name": "english"
                    }
                },
                {
                    "id": 48206,
                    "position": 8,
                    "char_type_name": "word",
                    "v1_page": 241,
                    "text_uthmani": "يُغَاثُ",
                    "text_uthmani_simple": "يغاث",
                    "code_v1": "ﮤ",
                    "page_number": 241,
                    "line_number": 9,
                    "text": "يُغَاثُ",
                    "translation": {
                        "text": "will be given abundant rain",
                        "language_name": "english"
                    }
                },
                {
                    "id": 48207,
                    "position": 9,
                    "char_type_name": "word",
                    "v1_page": 241,
                    "text_uthmani": "ٱلنَّاسُ",
                    "text_uthmani_simple": "الناس",
                    "code_v1": "ﮥ",
                    "page_number": 241,
                    "line_number": 9,
                    "text": "ٱلنَّاسُ",
                    "translation": {
                        "text": "the people",
                        "language_name": "english"
                    }
                },
                {
                    "id": 48208,
                    "position": 10,
                    "char_type_name": "word",
                    "v1_page": 241,
                    "text_uthmani": "وَفِيهِ",
                    "text_uthmani_simple": "وفيه",
                    "code_v1": "ﮦ",
                    "page_number": 241,
                    "line_number": 9,
                    "text": "وَفِيهِ",
                    "translation": {
                        "text": "and in it",
                        "language_name": "english"
                    }
                },
                {
                    "id": 48209,
                    "position": 11,
                    "char_type_name": "word",
                    "v1_page": 241,
                    "text_uthmani": "يَعْصِرُونَ",
                    "text_uthmani_simple": "يعصرون",
                    "code_v1": "ﮧ",
                    "page_number": 241,
                    "line_number": 9,
                    "text": "يَعْصِرُونَ",
                    "translation": {
                        "text": "they will press",
                        "language_name": "english"
                    }
                },
                {
                    "id": 48210,
                    "position": 12,
                    "char_type_name": "end",
                    "v1_page": 241,
                    "text_uthmani": "٤٩",
                    "text_uthmani_simple": "٤٩",
                    "code_v1": "ﮨ",
                    "page_number": 241,
                    "line_number": 9,
                    "text": "٤٩",
                    "translation": {
                        "text": "(49)",
                        "language_name": "english"
                    }
                }
            ]
        },
        {
            "id": 1646,
            "verse_number": 50,
            "verse_key": "12:50",
            "hizb_number": 24,
            "rub_el_hizb_number": 96,
            "ruku_number": 199,
            "manzil_number": 3,
            "sajdah_number": null,
            "text_uthmani_simple": "وقال الملك ائتونى به فلما جاءه الرسول قال ارجع الى ربك فسـله ما بال النسوة التى قطعن ايديهن ان ربى بكيدهن عليم",
            "text_uthmani": "وَقَالَ ٱلْمَلِكُ ٱئْتُونِى بِهِۦ ۖ فَلَمَّا جَآءَهُ ٱلرَّسُولُ قَالَ ٱرْجِعْ إِلَىٰ رَبِّكَ فَسْـَٔلْهُ مَا بَالُ ٱلنِّسْوَةِ ٱلَّـٰتِى قَطَّعْنَ أَيْدِيَهُنَّ ۚ إِنَّ رَبِّى بِكَيْدِهِنَّ عَلِيمٌ",
            "page_number": 241,
            "juz_number": 12,
            "words": [
                {
                    "id": 48860,
                    "position": 1,
                    "char_type_name": "word",
                    "v1_page": 241,
                    "text_uthmani": "وَقَالَ",
                    "text_uthmani_simple": "وقال",
                    "code_v1": "ﮩ",
                    "page_number": 241,
                    "line_number": 9,
                    "text": "وَقَالَ",
                    "translation": {
                        "text": "And said",
                        "language_name": "english"
                    }
                },
                {
                    "id": 48861,
                    "position": 2,
                    "char_type_name": "word",
                    "v1_page": 241,
                    "text_uthmani": "ٱلْمَلِكُ",
                    "text_uthmani_simple": "الملك",
                    "code_v1": "ﮪ",
                    "page_number": 241,
                    "line_number": 9,
                    "text": "ٱلْمَلِكُ",
                    "translation": {
                        "text": "the king",
                        "language_name": "english"
                    }
                },
                {
                    "id": 48862,
                    "position": 3,
                    "char_type_name": "word",
                    "v1_page": 241,
                    "text_uthmani": "ٱئْتُونِى",
                    "text_uthmani_simple": "ائتونى",
                    "code_v1": "ﮫ",
                    "page_number": 241,
                    "line_number": 9,
                    "text": "ٱئْتُونِى",
                    "translation": {
                        "text": "Bring him to me",
                        "language_name": "english"
                    }
                },
                {
                    "id": 48863,
                    "position": 4,
                    "char_type_name": "word",
                    "v1_page": 241,
                    "text_uthmani": "بِهِۦ ۖ",
                    "text_uthmani_simple": "به",
                    "code_v1": "ﮬﮭ",
                    "page_number": 241,
                    "line_number": 10,
                    "text": "بِهِۦ ۖ",
                    "translation": {
                        "text": "Bring him to me",
                        "language_name": "english"
                    }
                },
                {
                    "id": 48865,
                    "position": 5,
                    "char_type_name": "word",
                    "v1_page": 241,
                    "text_uthmani": "فَلَمَّا",
                    "text_uthmani_simple": "فلما",
                    "code_v1": "ﮮ",
                    "page_number": 241,
                    "line_number": 10,
                    "text": "فَلَمَّا",
                    "translation": {
                        "text": "But when",
                        "language_name": "english"
                    }
                },
                {
                    "id": 48866,
                    "position": 6,
                    "char_type_name": "word",
                    "v1_page": 241,
                    "text_uthmani": "جَآءَهُ",
                    "text_uthmani_simple": "جاه",
                    "code_v1": "ﮯ",
                    "page_number": 241,
                    "line_number": 10,
                    "text": "جَآءَهُ",
                    "translation": {
                        "text": "came to him",
                        "language_name": "english"
                    }
                },
                {
                    "id": 48867,
                    "position": 7,
                    "char_type_name": "word",
                    "v1_page": 241,
                    "text_uthmani": "ٱلرَّسُولُ",
                    "text_uthmani_simple": "الرسول",
                    "code_v1": "ﮰ",
                    "page_number": 241,
                    "line_number": 10,
                    "text": "ٱلرَّسُولُ",
                    "translation": {
                        "text": "the messenger",
                        "language_name": "english"
                    }
                },
                {
                    "id": 48868,
                    "position": 8,
                    "char_type_name": "word",
                    "v1_page": 241,
                    "text_uthmani": "قَالَ",
                    "text_uthmani_simple": "قال",
                    "code_v1": "ﮱ",
                    "page_number": 241,
                    "line_number": 10,
                    "text": "قَالَ",
                    "translation": {
                        "text": "he said",
                        "language_name": "english"
                    }
                },
                {
                    "id": 48869,
                    "position": 9,
                    "char_type_name": "word",
                    "v1_page": 241,
                    "text_uthmani": "ٱرْجِعْ",
                    "text_uthmani_simple": "ارجع",
                    "code_v1": "ﯓ",
                    "page_number": 241,
                    "line_number": 10,
                    "text": "ٱرْجِعْ",
                    "translation": {
                        "text": "Return",
                        "language_name": "english"
                    }
                },
                {
                    "id": 48870,
                    "position": 10,
                    "char_type_name": "word",
                    "v1_page": 241,
                    "text_uthmani": "إِلَىٰ",
                    "text_uthmani_simple": "الى",
                    "code_v1": "ﯔ",
                    "page_number": 241,
                    "line_number": 10,
                    "text": "إِلَىٰ",
                    "translation": {
                        "text": "to",
                        "language_name": "english"
                    }
                },
                {
                    "id": 48871,
                    "position": 11,
                    "char_type_name": "word",
                    "v1_page": 241,
                    "text_uthmani": "رَبِّكَ",
                    "text_uthmani_simple": "ربك",
                    "code_v1": "ﯕ",
                    "page_number": 241,
                    "line_number": 10,
                    "text": "رَبِّكَ",
                    "translation": {
                        "text": "your lord",
                        "language_name": "english"
                    }
                },
                {
                    "id": 48872,
                    "position": 12,
                    "char_type_name": "word",
                    "v1_page": 241,
                    "text_uthmani": "فَسْـَٔلْهُ",
                    "text_uthmani_simple": "فسـله",
                    "code_v1": "ﯖ",
                    "page_number": 241,
                    "line_number": 10,
                    "text": "فَسْـَٔلْهُ",
                    "translation": {
                        "text": "and ask him",
                        "language_name": "english"
                    }
                },
                {
                    "id": 48873,
                    "position": 13,
                    "char_type_name": "word",
                    "v1_page": 241,
                    "text_uthmani": "مَا",
                    "text_uthmani_simple": "ما",
                    "code_v1": "ﯗ",
                    "page_number": 241,
                    "line_number": 10,
                    "text": "مَا",
                    "translation": {
                        "text": "what",
                        "language_name": "english"
                    }
                },
                {
                    "id": 48874,
                    "position": 14,
                    "char_type_name": "word",
                    "v1_page": 241,
                    "text_uthmani": "بَالُ",
                    "text_uthmani_simple": "بال",
                    "code_v1": "ﯘ",
                    "page_number": 241,
                    "line_number": 10,
                    "text": "بَالُ",
                    "translation": {
                        "text": "(is the) case",
                        "language_name": "english"
                    }
                },
                {
                    "id": 48875,
                    "position": 15,
                    "char_type_name": "word",
                    "v1_page": 241,
                    "text_uthmani": "ٱلنِّسْوَةِ",
                    "text_uthmani_simple": "النسوة",
                    "code_v1": "ﯙ",
                    "page_number": 241,
                    "line_number": 11,
                    "text": "ٱلنِّسْوَةِ",
                    "translation": {
                        "text": "(of) the women",
                        "language_name": "english"
                    }
                },
                {
                    "id": 48876,
                    "position": 16,
                    "char_type_name": "word",
                    "v1_page": 241,
                    "text_uthmani": "ٱلَّـٰتِى",
                    "text_uthmani_simple": "الـتى",
                    "code_v1": "ﯚ",
                    "page_number": 241,
                    "line_number": 11,
                    "text": "ٱلَّـٰتِى",
                    "translation": {
                        "text": "who",
                        "language_name": "english"
                    }
                },
                {
                    "id": 48877,
                    "position": 17,
                    "char_type_name": "word",
                    "v1_page": 241,
                    "text_uthmani": "قَطَّعْنَ",
                    "text_uthmani_simple": "قطعن",
                    "code_v1": "ﯛ",
                    "page_number": 241,
                    "line_number": 11,
                    "text": "قَطَّعْنَ",
                    "translation": {
                        "text": "cut",
                        "language_name": "english"
                    }
                },
                {
                    "id": 48878,
                    "position": 18,
                    "char_type_name": "word",
                    "v1_page": 241,
                    "text_uthmani": "أَيْدِيَهُنَّ ۚ",
                    "text_uthmani_simple": "ايديهن",
                    "code_v1": "ﯜﯝ",
                    "page_number": 241,
                    "line_number": 11,
                    "text": "أَيْدِيَهُنَّ ۚ",
                    "translation": {
                        "text": "their hands",
                        "language_name": "english"
                    }
                },
                {
                    "id": 48880,
                    "position": 19,
                    "char_type_name": "word",
                    "v1_page": 241,
                    "text_uthmani": "إِنَّ",
                    "text_uthmani_simple": "ان",
                    "code_v1": "ﯞ",
                    "page_number": 241,
                    "line_number": 11,
                    "text": "إِنَّ",
                    "translation": {
                        "text": "Indeed",
                        "language_name": "english"
                    }
                },
                {
                    "id": 48881,
                    "position": 20,
                    "char_type_name": "word",
                    "v1_page": 241,
                    "text_uthmani": "رَبِّى",
                    "text_uthmani_simple": "ربى",
                    "code_v1": "ﯟ",
                    "page_number": 241,
                    "line_number": 11,
                    "text": "رَبِّى",
                    "translation": {
                        "text": "my Lord",
                        "language_name": "english"
                    }
                },
                {
                    "id": 48882,
                    "position": 21,
                    "char_type_name": "word",
                    "v1_page": 241,
                    "text_uthmani": "بِكَيْدِهِنَّ",
                    "text_uthmani_simple": "بكيدهن",
                    "code_v1": "ﯠ",
                    "page_number": 241,
                    "line_number": 11,
                    "text": "بِكَيْدِهِنَّ",
                    "translation": {
                        "text": "of their plot",
                        "language_name": "english"
                    }
                },
                {
                    "id": 48883,
                    "position": 22,
                    "char_type_name": "word",
                    "v1_page": 241,
                    "text_uthmani": "عَلِيمٌۭ",
                    "text_uthmani_simple": "عليمۭ",
                    "code_v1": "ﯡ",
                    "page_number": 241,
                    "line_number": 11,
                    "text": "عَلِيمٌۭ",
                    "translation": {
                        "text": "(is) All-Knower",
                        "language_name": "english"
                    }
                },
                {
                    "id": 48884,
                    "position": 23,
                    "char_type_name": "end",
                    "v1_page": 241,
                    "text_uthmani": "٥٠",
                    "text_uthmani_simple": "٥٠",
                    "code_v1": "ﯢ",
                    "page_number": 241,
                    "line_number": 11,
                    "text": "٥٠",
                    "translation": {
                        "text": "(50)",
                        "language_name": "english"
                    }
                }
            ]
        },
        {
            "id": 1647,
            "verse_number": 51,
            "verse_key": "12:51",
            "hizb_number": 24,
            "rub_el_hizb_number": 96,
            "ruku_number": 199,
            "manzil_number": 3,
            "sajdah_number": null,
            "text_uthmani_simple": "قال ما خطبكن اذ رودتن يوسف عن نفسه قلن حش لله ما علمنا عليه من سوء قالت امرات العزيز الـن حصحص الحق انا۠ رودته عن نفسه وانه لمن الصدقين",
            "text_uthmani": "قَالَ مَا خَطْبُكُنَّ إِذْ رَٰوَدتُّنَّ يُوسُفَ عَن نَّفْسِهِۦ ۚ قُلْنَ حَـٰشَ لِلَّهِ مَا عَلِمْنَا عَلَيْهِ مِن سُوٓءٍ ۚ قَالَتِ ٱمْرَأَتُ ٱلْعَزِيزِ ٱلْـَٔـٰنَ حَصْحَصَ ٱلْحَقُّ أَنَا۠ رَٰوَدتُّهُۥ عَن نَّفْسِهِۦ وَإِنَّهُۥ لَمِنَ ٱلصَّـٰدِقِينَ",
            "page_number": 241,
            "juz_number": 12,
            "words": [
                {
                    "id": 49379,
                    "position": 1,
                    "char_type_name": "word",
                    "v1_page": 241,
                    "text_uthmani": "قَالَ",
                    "text_uthmani_simple": "قال",
                    "code_v1": "ﯣ",
                    "page_number": 241,
                    "line_number": 11,
                    "text": "قَالَ",
                    "translation": {
                        "text": "He said",
                        "language_name": "english"
                    }
                },
                {
                    "id": 49380,
                    "position": 2,
                    "char_type_name": "word",
                    "v1_page": 241,
                    "text_uthmani": "مَا",
                    "text_uthmani_simple": "ما",
                    "code_v1": "ﯤ",
                    "page_number": 241,
                    "line_number": 12,
                    "text": "مَا",
                    "translation": {
                        "text": "What",
                        "language_name": "english"
                    }
                },
                {
                    "id": 49381,
                    "position": 3,
                    "char_type_name": "word",
                    "v1_page": 241,
                    "text_uthmani": "خَطْبُكُنَّ",
                    "text_uthmani_simple": "خطبكن",
                    "code_v1": "ﯥ",
                    "page_number": 241,
                    "line_number": 12,
                    "text": "خَطْبُكُنَّ",
                    "translation": {
                        "text": "(was) your affair",
                        "language_name": "english"
                    }
                },
                {
                    "id": 49382,
                    "position": 4,
                    "char_type_name": "word",
                    "v1_page": 241,
                    "text_uthmani": "إِذْ",
                    "text_uthmani_simple": "اذ",
                    "code_v1": "ﯦ",
                    "page_number": 241,
                    "line_number": 12,
                    "text": "إِذْ",
                    "translation": {
                        "text": "when",
                        "language_name": "english"
                    }
                },
                {
                    "id": 49383,
                    "position": 5,
                    "char_type_name": "word",
                    "v1_page": 241,
                    "text_uthmani": "رَٰوَدتُّنَّ",
                    "text_uthmani_simple": "رودتن",
                    "code_v1": "ﯧ",
                    "page_number": 241,
                    "line_number": 12,
                    "text": "رَٰوَدتُّنَّ",
                    "translation": {
                        "text": "you sought to seduce",
                        "language_name": "english"
                    }
                },
                {
                    "id": 49384,
                    "position": 6,
                    "char_type_name": "word",
                    "v1_page": 241,
                    "text_uthmani": "يُوسُفَ",
                    "text_uthmani_simple": "يوسف",
                    "code_v1": "ﯨ",
                    "page_number": 241,
                    "line_number": 12,
                    "text": "يُوسُفَ",
                    "translation": {
                        "text": "Yusuf",
                        "language_name": "english"
                    }
                },
                {
                    "id": 49385,
                    "position": 7,
                    "char_type_name": "word",
                    "v1_page": 241,
                    "text_uthmani": "عَن",
                    "text_uthmani_simple": "عن",
                    "code_v1": "ﯩ",
                    "page_number": 241,
                    "line_number": 12,
                    "text": "عَن",
                    "translation": {
                        "text": "from",
                        "language_name": "english"
                    }
                },
                {
                    "id": 49386,
                    "position": 8,
                    "char_type_name": "word",
                    "v1_page": 241,
                    "text_uthmani": "نَّفْسِهِۦ ۚ",
                    "text_uthmani_simple": "نفسه",
                    "code_v1": "ﯪﯫ",
                    "page_number": 241,
                    "line_number": 12,
                    "text": "نَّفْسِهِۦ ۚ",
                    "translation": {
                        "text": "himself",
                        "language_name": "english"
                    }
                },
                {
                    "id": 49388,
                    "position": 9,
                    "char_type_name": "word",
                    "v1_page": 241,
                    "text_uthmani": "قُلْنَ",
                    "text_uthmani_simple": "قلن",
                    "code_v1": "ﯬ",
                    "page_number": 241,
                    "line_number": 12,
                    "text": "قُلْنَ",
                    "translation": {
                        "text": "They said",
                        "language_name": "english"
                    }
                },
                {
                    "id": 49389,
                    "position": 10,
                    "char_type_name": "word",
                    "v1_page": 241,
                    "text_uthmani": "حَـٰشَ",
                    "text_uthmani_simple": "حـش",
                    "code_v1": "ﯭ",
                    "page_number": 241,
                    "line_number": 12,
                    "text": "حَـٰشَ",
                    "translation": {
                        "text": "Allah forbid",
                        "language_name": "english"
                    }
                },
                {
                    "id": 49390,
                    "position": 11,
                    "char_type_name": "word",
                    "v1_page": 241,
                    "text_uthmani": "لِلَّهِ",
                    "text_uthmani_simple": "لله",
                    "code_v1": "ﯮ",
                    "page_number": 241,
                    "line_number": 12,
                    "text": "لِلَّهِ",
                    "translation": {
                        "text": "Allah forbid",
                        "language_name": "english"
                    }
                },
                {
                    "id": 49391,
                    "position": 12,
                    "char_type_name": "word",
                    "v1_page": 241,
                    "text_uthmani": "مَا",
                    "text_uthmani_simple": "ما",
                    "code_v1": "ﯯ",
                    "page_number": 241,
                    "line_number": 13,
                    "text": "مَا",
                    "translation": {
                        "text": "Not",
                        "language_name": "english"
                    }
                },
                {
                    "id": 49392,
                    "position": 13,
                    "char_type_name": "word",
                    "v1_page": 241,
                    "text_uthmani": "عَلِمْنَا",
                    "text_uthmani_simple": "علمنا",
                    "code_v1": "ﯰ",
                    "page_number": 241,
                    "line_number": 13,
                    "text": "عَلِمْنَا",
                    "translation": {
                        "text": "we know",
                        "language_name": "english"
                    }
                },
                {
                    "id": 49393,
                    "position": 14,
                    "char_type_name": "word",
                    "v1_page": 241,
                    "text_uthmani": "عَلَيْهِ",
                    "text_uthmani_simple": "عليه",
                    "code_v1": "ﯱ",
                    "page_number": 241,
                    "line_number": 13,
                    "text": "عَلَيْهِ",
                    "translation": {
                        "text": "about him",
                        "language_name": "english"
                    }
                },
                {
                    "id": 49394,
                    "position": 15,
                    "char_type_name": "word",
                    "v1_page": 241,
                    "text_uthmani": "مِن",
                    "text_uthmani_simple": "من",
                    "code_v1": "ﯲ",
                    "page_number": 241,
                    "line_number": 13,
                    "text": "مِن",
                    "translation": {
                        "text": "any",
                        "language_name": "english"
                    }
                },
                {
                    "id": 49395,
                    "position": 16,
                    "char_type_name": "word",
                    "v1_page": 241,
                    "text_uthmani": "سُوٓءٍۢ ۚ",
                    "text_uthmani_simple": "سو",
                    "code_v1": "ﯳﯴ",
                    "page_number": 241,
                    "line_number": 13,
                    "text": "سُوٓءٍۢ ۚ",
                    "translation": {
                        "text": "evil",
                        "language_name": "english"
                    }
                },
                {
                    "id": 49397,
                    "position": 17,
                    "char_type_name": "word",
                    "v1_page": 241,
                    "text_uthmani": "قَالَتِ",
                    "text_uthmani_simple": "قالت",
                    "code_v1": "ﯵ",
                    "page_number": 241,
                    "line_number": 13,
                    "text": "قَالَتِ",
                    "translation": {
                        "text": "Said",
                        "language_name": "english"
                    }
                },
                {
                    "id": 49398,
                    "position": 18,
                    "char_type_name": "word",
                    "v1_page": 241,
                    "text_uthmani": "ٱمْرَأَتُ",
                    "text_uthmani_simple": "امرات",
                    "code_v1": "ﯶ",
                    "page_number": 241,
                    "line_number": 13,
                    "text": "ٱمْرَأَتُ",
                    "translation": {
                        "text": "(the) wife",
                        "language_name": "english"
                    }
                },
                {
                    "id": 49399,
                    "position": 19,
                    "char_type_name": "word",
                    "v1_page": 241,
                    "text_uthmani": "ٱلْعَزِيزِ",
                    "text_uthmani_simple": "العزيز",
                    "code_v1": "ﯷ",
                    "page_number": 241,
                    "line_number": 13,
                    "text": "ٱلْعَزِيزِ",
                    "translation": {
                        "text": "(of) Aziz",
                        "language_name": "english"
                    }
                },
                {
                    "id": 49400,
                    "position": 20,
                    "char_type_name": "word",
                    "v1_page": 241,
                    "text_uthmani": "ٱلْـَٔـٰنَ",
                    "text_uthmani_simple": "الــن",
                    "code_v1": "ﯸ",
                    "page_number": 241,
                    "line_number": 13,
                    "text": "ٱلْـَٔـٰنَ",
                    "translation": {
                        "text": "Now",
                        "language_name": "english"
                    }
                },
                {
                    "id": 49401,
                    "position": 21,
                    "char_type_name": "word",
                    "v1_page": 241,
                    "text_uthmani": "حَصْحَصَ",
                    "text_uthmani_simple": "حصحص",
                    "code_v1": "ﯹ",
                    "page_number": 241,
                    "line_number": 13,
                    "text": "حَصْحَصَ",
                    "translation": {
                        "text": "(is) manifest",
                        "language_name": "english"
                    }
                },
                {
                    "id": 49402,
                    "position": 22,
                    "char_type_name": "word",
                    "v1_page": 241,
                    "text_uthmani": "ٱلْحَقُّ",
                    "text_uthmani_simple": "الحق",
                    "code_v1": "ﯺ",
                    "page_number": 241,
                    "line_number": 14,
                    "text": "ٱلْحَقُّ",
                    "translation": {
                        "text": "the truth",
                        "language_name": "english"
                    }
                },
                {
                    "id": 49403,
                    "position": 23,
                    "char_type_name": "word",
                    "v1_page": 241,
                    "text_uthmani": "أَنَا۠",
                    "text_uthmani_simple": "انا۠",
                    "code_v1": "ﯻ",
                    "page_number": 241,
                    "line_number": 14,
                    "text": "أَنَا۠",
                    "translation": {
                        "text": "I",
                        "language_name": "english"
                    }
                },
                {
                    "id": 49404,
                    "position": 24,
                    "char_type_name": "word",
                    "v1_page": 241,
                    "text_uthmani": "رَٰوَدتُّهُۥ",
                    "text_uthmani_simple": "رودته",
                    "code_v1": "ﯼ",
                    "page_number": 241,
                    "line_number": 14,
                    "text": "رَٰوَدتُّهُۥ",
                    "translation": {
                        "text": "sought to seduce him",
                        "language_name": "english"
                    }
                },
                {
                    "id": 49405,
                    "position": 25,
                    "char_type_name": "word",
                    "v1_page": 241,
                    "text_uthmani": "عَن",
                    "text_uthmani_simple": "عن",
                    "code_v1": "ﯽ",
                    "page_number": 241,
                    "line_number": 14,
                    "text": "عَن",
                    "translation": {
                        "text": "from",
                        "language_name": "english"
                    }
                },
                {
                    "id": 49406,
                    "position": 26,
                    "char_type_name": "word",
                    "v1_page": 241,
                    "text_uthmani": "نَّفْسِهِۦ",
                    "text_uthmani_simple": "نفسه",
                    "code_v1": "ﯾ",
                    "page_number": 241,
                    "line_number": 14,
                    "text": "نَّفْسِهِۦ",
                    "translation": {
                        "text": "himself",
                        "language_name": "english"
                    }
                },
                {
                    "id": 49407,
                    "position": 27,
                    "char_type_name": "word",
                    "v1_page": 241,
                    "text_uthmani": "وَإِنَّهُۥ",
                    "text_uthmani_simple": "وانه",
                    "code_v1": "ﯿ",
                    "page_number": 241,
                    "line_number": 14,
                    "text": "وَإِنَّهُۥ",
                    "translation": {
                        "text": "and indeed, he",
                        "language_name": "english"
                    }
                },
                {
                    "id": 49408,
                    "position": 28,
                    "char_type_name": "word",
                    "v1_page": 241,
                    "text_uthmani": "لَمِنَ",
                    "text_uthmani_simple": "لمن",
                    "code_v1": "ﰀ",
                    "page_number": 241,
                    "line_number": 14,
                    "text": "لَمِنَ",
                    "translation": {
                        "text": "(is) surely of",
                        "language_name": "english"
                    }
                },
                {
                    "id": 49409,
                    "position": 29,
                    "char_type_name": "word",
                    "v1_page": 241,
                    "text_uthmani": "ٱلصَّـٰدِقِينَ",
                    "text_uthmani_simple": "الصـدقين",
                    "code_v1": "ﰁ",
                    "page_number": 241,
                    "line_number": 14,
                    "text": "ٱلصَّـٰدِقِينَ",
                    "translation": {
                        "text": "the truthful",
                        "language_name": "english"
                    }
                },
                {
                    "id": 49410,
                    "position": 30,
                    "char_type_name": "end",
                    "v1_page": 241,
                    "text_uthmani": "٥١",
                    "text_uthmani_simple": "٥١",
                    "code_v1": "ﰂ",
                    "page_number": 241,
                    "line_number": 14,
                    "text": "٥١",
                    "translation": {
                        "text": "(51)",
                        "language_name": "english"
                    }
                }
            ]
        },
        {
            "id": 1648,
            "verse_number": 52,
            "verse_key": "12:52",
            "hizb_number": 24,
            "rub_el_hizb_number": 96,
            "ruku_number": 199,
            "manzil_number": 3,
            "sajdah_number": null,
            "text_uthmani_simple": "ذلك ليعلم انى لم اخنه بالغيب وان الله لا يهدى كيد الخائنين",
            "text_uthmani": "ذَٰلِكَ لِيَعْلَمَ أَنِّى لَمْ أَخُنْهُ بِٱلْغَيْبِ وَأَنَّ ٱللَّهَ لَا يَهْدِى كَيْدَ ٱلْخَآئِنِينَ",
            "page_number": 241,
            "juz_number": 12,
            "words": [
                {
                    "id": 50152,
                    "position": 1,
                    "char_type_name": "word",
                    "v1_page": 241,
                    "text_uthmani": "ذَٰلِكَ",
                    "text_uthmani_simple": "ذلك",
                    "code_v1": "ﰃ",
                    "page_number": 241,
                    "line_number": 14,
                    "text": "ذَٰلِكَ",
                    "translation": {
                        "text": "That",
                        "language_name": "english"
                    }
                },
                {
                    "id": 50153,
                    "position": 2,
                    "char_type_name": "word",
                    "v1_page": 241,
                    "text_uthmani": "لِيَعْلَمَ",
                    "text_uthmani_simple": "ليعلم",
                    "code_v1": "ﰄ",
                    "page_number": 241,
                    "line_number": 15,
                    "text": "لِيَعْلَمَ",
                    "translation": {
                        "text": "he may know",
                        "language_name": "english"
                    }
                },
                {
                    "id": 50154,
                    "position": 3,
                    "char_type_name": "word",
                    "v1_page": 241,
                    "text_uthmani": "أَنِّى",
                    "text_uthmani_simple": "انى",
                    "code_v1": "ﰅ",
                    "page_number": 241,
                    "line_number": 15,
                    "text": "أَنِّى",
                    "translation": {
                        "text": "that I",
                        "language_name": "english"
                    }
                },
                {
                    "id": 50155,
                    "position": 4,
                    "char_type_name": "word",
                    "v1_page": 241,
                    "text_uthmani": "لَمْ",
                    "text_uthmani_simple": "لم",
                    "code_v1": "ﰆ",
                    "page_number": 241,
                    "line_number": 15,
                    "text": "لَمْ",
                    "translation": {
                        "text": "not",
                        "language_name": "english"
                    }
                },
                {
                    "id": 50156,
                    "position": 5,
                    "char_type_name": "word",
                    "v1_page": 241,
                    "text_uthmani": "أَخُنْهُ",
                    "text_uthmani_simple": "اخنه",
                    "code_v1": "ﰇ",
                    "page_number": 241,
                    "line_number": 15,
                    "text": "أَخُنْهُ",
                    "translation": {
                        "text": "[I] betray him",
                        "language_name": "english"
                    }
                },
                {
                    "id": 50157,
                    "position": 6,
                    "char_type_name": "word",
                    "v1_page": 241,
                    "text_uthmani": "بِٱلْغَيْبِ",
                    "text_uthmani_simple": "بالغيب",
                    "code_v1": "ﰈ",
                    "page_number": 241,
                    "line_number": 15,
                    "text": "بِٱلْغَيْبِ",
                    "translation": {
                        "text": "in secret",
                        "language_name": "english"
                    }
                },
                {
                    "id": 50158,
                    "position": 7,
                    "char_type_name": "word",
                    "v1_page": 241,
                    "text_uthmani": "وَأَنَّ",
                    "text_uthmani_simple": "وان",
                    "code_v1": "ﰉ",
                    "page_number": 241,
                    "line_number": 15,
                    "text": "وَأَنَّ",
                    "translation": {
                        "text": "and that",
                        "language_name": "english"
                    }
                },
                {
                    "id": 50159,
                    "position": 8,
                    "char_type_name": "word",
                    "v1_page": 241,
                    "text_uthmani": "ٱللَّهَ",
                    "text_uthmani_simple": "الله",
                    "code_v1": "ﰊ",
                    "page_number": 241,
                    "line_number": 15,
                    "text": "ٱللَّهَ",
                    "translation": {
                        "text": "Allah",
                        "language_name": "english"
                    }
                },
                {
                    "id": 50160,
                    "position": 9,
                    "char_type_name": "word",
                    "v1_page": 241,
                    "text_uthmani": "لَا",
                    "text_uthmani_simple": "لا",
                    "code_v1": "ﰋ",
                    "page_number": 241,
                    "line_number": 15,
                    "text": "لَا",
                    "translation": {
                        "text": "(does) not",
                        "language_name": "english"
                    }
                },
                {
                    "id": 50161,
                    "position": 10,
                    "char_type_name": "word",
                    "v1_page": 241,
                    "text_uthmani": "يَهْدِى",
                    "text_uthmani_simple": "يهدى",
                    "code_v1": "ﰌ",
                    "page_number": 241,
                    "line_number": 15,
                    "text": "يَهْدِى",
                    "translation": {
                        "text": "guide",
                        "language_name": "english"
                    }
                },
                {
                    "id": 50162,
                    "position": 11,
                    "char_type_name": "word",
                    "v1_page": 241,
                    "text_uthmani": "كَيْدَ",
                    "text_uthmani_simple": "كيد",
                    "code_v1": "ﰍ",
                    "page_number": 241,
                    "line_number": 15,
                    "text": "كَيْدَ",
                    "translation": {
                        "text": "(the) plan",
                        "language_name": "english"
                    }
                },
                {
                    "id": 50163,
                    "position": 12,
                    "char_type_name": "word",
                    "v1_page": 241,
                    "text_uthmani": "ٱلْخَآئِنِينَ",
                    "text_uthmani_simple": "الخائنين",
                    "code_v1": "ﰎ",
                    "page_number": 241,
                    "line_number": 15,
                    "text": "ٱلْخَآئِنِينَ",
                    "translation": {
                        "text": "(of) the betrayers",
                        "language_name": "english"
                    }
                },
                {
                    "id": 50164,
                    "position": 13,
                    "char_type_name": "end",
                    "v1_page": 241,
                    "text_uthmani": "٥٢",
                    "text_uthmani_simple": "٥٢",
                    "code_v1": "ﰏ",
                    "page_number": 241,
                    "line_number": 15,
                    "text": "٥٢",
                    "translation": {
                        "text": "(52)",
                        "language_name": "english"
                    }
                }
            ]
        }
    ]
}